Workbook

Sheet Start Here
B2: AI Engineer Roadmap 2027: Tracker
B3: AI Anytime · Edition 1.0 · September 2026 · Licensed for personal use
B5: How to use this workbook
B6: 1. Open the Dashboard tab and fill the yellow cells: your name, track, start date (first day of Month 1), weekly hours, target role and city.
B7: 2. Roadmap: planned dates calculate from your start date. Change Status as you finish each month (only after its assessment).
B8: 3. Skills Matrix: update Current level (0-5) and Evidence link at every monthly review. 'Demonstrated' needs a link someone else can check.
B9: 4. Learning Tracker lists every resource the roadmap assigns, month by month. Log hours and the artifact each resource produced.
B10: 5. Projects, Capstone and GitHub tabs are your portfolio command centre.
B11: 6. Question Bank: rate confidence 1-3 after practising; Next review is calculated (1 = 3 days, 2 = 7 days, 3 = 14 days).
B12: 7. Mock Interviews, Job Research, Target Companies, Applications and Networking run your job search. The Dashboard shows funnel conversion.
B13: 8. Weekly Review every Sunday (20 minutes). Monthly Review on the last Sunday of each month (60 minutes).
B15: Yellow cells are for your input. Black header rows are fixed. Filters are enabled on every tab.
... B24: 0 Awareness: can explain · 1 Guided: can follow a tutorial · 2 Independent: builds without copying · 3 Production: deploys and operates · 4 Advanced: designs and debugs · 5 Expert: makes trade-offs, teaches, innovates

Sheet Dashboard
B2: Dashboard
B3: Fill the yellow cells. Everything else updates automatically.
B5: Name
B6: Track | C6: 1. Beginner → AI Engineer
B7: Start date (Month 1)
B8: Weekly hours | C8: 15
B9: Target role | C9: AI Engineer
B10: Target city | C10: Hyderabad
B12: PROGRESS | E12: INTERVIEWS
B13: Roadmap months completed | C13: =COUNTIF(Roadmap!K:K,"Done")&" / 13" | E13: Questions practised | F13: =COUNTA('Question Bank'!J2:J301)&" / 300"
B14: Current month (by date) | C14: =IF(C7="","set start date",IFERROR(MAX(0,MIN(12,DATEDIF(C7,TODAY(),"m")+1)),"not started yet")) | E14: Average confidence (1-3) | F14: =IFERROR(ROUND(AVERAGE('Question Bank'!I2:I301),2),"-")
B15: Hours logged (Weekly Review) | C15: =SUM('Weekly Review'!G:G) | E15: Questions due for review | F15: =COUNTIFS('Question Bank'!K2:K301,"<="&TODAY(),'Question Bank'!K2:K301,"<>")
B16: Hours logged (Learning Tracker) | C16: =SUM('Learning Tracker'!F:F) | E16: Mock interview average (1-4) | F16: =IFERROR(ROUND(AVERAGE('Mock Interviews'!N:N),2),"-")
B17: SKILLS | E17: JOB SEARCH
B18: Skills demonstrated | C18: =COUNTIF('Skills Matrix'!G:G,"Demonstrated")&" / 52" | E18: Applications sent | F18: =COUNTA(Applications!B2:B1000)
B19: Skills at or above target | C19: =SUMPRODUCT(('Skills Matrix'!F2:F53<>"")*('Skills Matrix'!F2:F53>='Skills Matrix'!E2:E53))&" / 52" | E19: With referral | F19: =COUNTIF(Applications!F:F,"Yes")
B20: Skills interview ready | C20: =COUNTIF('Skills Matrix'!J:J,"Yes")&" / 52" | E20: Reached screen or later | F20: =COUNTIF(Applications!G:G,"Screen")+COUNTIF(Applications!G:G,"Technical")+COUNTIF(Applications!G:G,"Final")+COUNTIF(Applications!G:G,"Offer")
B21: PORTFOLIO | E21: Reached final round or offer | F21: =COUNTIF(Applications!G:G,"Final")+COUNTIF(Applications!G:G,"Offer")
B22: Projects done | C22: =COUNTIF(Projects!L:L,"Done")&" / 7" | E22: Offers | F22: =COUNTIF(Applications!G:G,"Offer")
B23: Projects interview ready | C23: =COUNTIF(Projects!M:M,"Yes")&" / 7" | E23: Application → screen rate | F23: =IFERROR(TEXT(F20/F18,"0%"),"-")
B24: Capstone rubric score | C24: =Capstone!C40&" / 60" | E24: Networking contacts | F24: =COUNTA(Networking!A2:A1000)

Sheet Roadmap
A1: Month | B1: Theme | C1: Planned start | D1: Planned end | E1: Milestone | F1: Goal | G1: Build | H1: Artifact | I1: Assessment | J1: Hours | K1: Status | L1: Completed on | M1: Rubric avg (1-4) | N1: Notes
A2: 0 | B2: On-ramp: from zero to writing Python | C2: =IF(Dashboard!$C$7="","",EDATE(Dashboard!$C$7,A2-1)) | D2: =IF(C2="","",EDATE(C2,1)-1) | E2: Only for non-tech learners and students who cannot code yet (6-8 weeks) | F2: Write small Python programs without copying, use the terminal and push code to GitHub. | G2: 3 small programs: expense tracker (CSV), quiz game, file organizer | H2: GitHub profile with 3 repos, each with a short README | I2: Solve 5 unseen beginner problems in 90 minutes without AI help. Pass = 4/5 working. | J2: 60-90 | K2: Not started
A3: 1 | B3: Engineering foundations and your first AI app | C3: =IF(Dashboard!$C$7="","",EDATE(Dashboard!$C$7,A3-1)) | D3: =IF(C3="","",EDATE(C3,1)-1) | E3: 30-day milestone: foundation + first working AI application | F3: Set up a professional dev environment and ship a working command-line AI tool that calls an LLM API. | G3: AI CLI tool: summarizes a folder of text/PDF files into structured notes (title, key points, action items) saved as JSON and Markdown | H3: Repo 'ai-notes-cli' with README, usage GIF, .env.example, basic tests | I3: Rebuild the CLI core from an empty folder in 2 hours with docs only. Explain every line in a 5-minute recording. | J3: 60 | K3: Not started
A4: 2 | B4: LLM engineering core | C4: =IF(Dashboard!$C$7="","",EDATE(Dashboard!$C$7,A4-1)) | D4: =IF(C4="","",EDATE(C4,1)-1) | E4: Project 1 shipped | F4: Build a production-style AI API that handles structured output, tool calling, model comparison, cost and latency tracking. | G4: Project 1: Production-style AI API (model comparison service) | H4: Dockerized API + benchmark table + architecture diagram + README | I4: Project 1 acceptance criteria met (see project ladder). Level 2 on S03, S18, S19, S20. | J4: 60 | K4: Not started
A5: 3 | B5: How LLMs actually work | C5: =IF(Dashboard!$C$7="","",EDATE(Dashboard!$C$7,A5-1)) | D5: =IF(C5="","",EDATE(C5,1)-1) | E5: Foundations that interviews test | F5: Understand neural networks, transformers and embeddings well enough to explain and debug model behaviour. | G5: Mini GPT notebook + 'embedding explorer' app that finds similar sentences in your own notes | H5: Notebook repo with explanations in your own words; small embedding search demo | I5: Whiteboard attention and a transformer block in 10 minutes. Reproduce P01 exercise. Level 2 on S13, S14, S15. | J5: 60-70 | K5: Not started
A6: 4 | B6: Retrieval-augmented generation | C6: =IF(Dashboard!$C$7="","",EDATE(Dashboard!$C$7,A6-1)) | D6: =IF(C6="","",EDATE(C6,1)-1) | E6: Project 2 shipped | F6: Build and evaluate a RAG system that answers from documents with citations and measured quality. | G6: Project 2: Evaluated RAG application | H6: Deployed RAG app + evaluation report + experiment log + architecture diagram | I6: Recall@5 and faithfulness reported on 100 questions; explain two failure cases and fixes. Level 3 on S23-S26. | J6: 60-70 | K6: Not started
A7: 5 | B7: Agents, tools and MCP | C7: =IF(Dashboard!$C$7="","",EDATE(Dashboard!$C$7,A7-1)) | D7: =IF(C7="","",EDATE(C7,1)-1) | E7: Project 3 shipped | F7: Build a tool-using agent with state, permissions and human approval, connected through MCP. | G7: Project 3: Tool-using agent | H7: Agent repo + MCP server + task success benchmark (20+ tasks, 5 runs each) + threat notes | I7: pass^1 and pass^5 reported on 20 tasks; approval gate demo; explain one failure trajectory. Level 3 on S28-S31. | J7: 60-70 | K7: Not started
A8: 6 | B8: Evaluation as an engineering system | C8: =IF(Dashboard!$C$7="","",EDATE(Dashboard!$C$7,A8-1)) | D8: =IF(C8="","",EDATE(C8,1)-1) | E8: 6-month milestone: production-ready portfolio + interview preparation starts | F8: Build a reusable evaluation harness and put quality gates into CI for Projects 2 and 3. | G8: Project 4: Reusable evaluation harness | H8: Eval harness package + CI workflow blocking regressions + eval dashboard screenshot | I8: CI fails on a deliberately broken prompt; judge agreement >= 80% with your labels. Start interview question bank: 5 questions/day. | J8: 60-70 | K8: Not started
A9: 7 | B9: Production hardening and AI security | C9: =IF(Dashboard!$C$7="","",EDATE(Dashboard!$C$7,A9-1)) | D9: =IF(C9="","",EDATE(C9,1)-1) | E9: Project 6 shipped | F9: Turn one project into a service you would trust with real users: auth, observability, cost controls, security testing. | G9: Project 6: Production AI service (hardened P2 or P3) | H9: Deployed service + dashboards + threat model + red-team report + runbook + cost report | I9: Run the production readiness checklist; all critical items pass. Level 3 on S40-S46. | J9: 60-70 | K9: Not started
A10: 8 | B10: Multimodal AI and fine-tuning | C10: =IF(Dashboard!$C$7="","",EDATE(Dashboard!$C$7,A10-1)) | D10: =IF(C10="","",EDATE(C10,1)-1) | E10: Project 5 shipped | F10: Build a document, vision or voice AI system and learn when fine-tuning beats prompting. | G10: Project 5: Multimodal system (document intelligence, visual QA, or voice agent) | H10: Repo + field-level accuracy report (or latency breakdown for voice) + fine-tune vs prompt comparison | I10: Accuracy or latency targets set in advance and met or explained. Level 2-3 on S16, S32-S34. | J10: 60-70 | K10: Not started
A11: 9 | B11: AI infrastructure, advanced retrieval and capstone design | C11: =IF(Dashboard!$C$7="","",EDATE(Dashboard!$C$7,A11-1)) | D11: =IF(C11="","",EDATE(C11,1)-1) | E11: Capstone design approved | F11: Understand serving economics and design a serious capstone before writing code. | G11: Capstone design document: problem, users, data, architecture, models, retrieval, agents, evaluation plan, security, deployment, economics, risks | H11: Design doc + architecture diagram + ADRs + serving benchmark notebook | I11: Peer or mentor review of design doc using the capstone rubric. Start networking: 5 conversations this month. | J11: 60-70 | K11: Not started
A12: 10 | B12: Capstone build | C12: =IF(Dashboard!$C$7="","",EDATE(Dashboard!$C$7,A12-1)) | D12: =IF(C12="","",EDATE(C12,1)-1) | E12: Capstone core working end to end | F12: Build the capstone's core workflow with evaluation from day one. | G12: Capstone v1: core workflow, eval set, traces | H12: Working demo on staging + eval report v1 | I12: Core user journey passes 80% of eval set. Resume and LinkedIn rewritten around projects. | J12: 70-80 | K12: Not started
A13: 11 | B13: Capstone production + system design preparation | C13: =IF(Dashboard!$C$7="","",EDATE(Dashboard!$C$7,A13-1)) | D13: =IF(C13="","",EDATE(C13,1)-1) | E13: Capstone deployed | F13: Harden, secure, deploy and document the capstone; begin structured interview preparation. | G13: Capstone v2: deployed with auth, monitoring, cost tracking, red-team report and full documentation | H13: Public demo, 3-minute video, README, design doc, eval report, cost report, failure analysis | I13: Capstone rubric score >= 80%. First 20 targeted applications sent. | J13: 70-80 | K13: Not started
A14: 12 | B14: Interview sprint and job search | C14: =IF(Dashboard!$C$7="","",EDATE(Dashboard!$C$7,A14-1)) | D14: =IF(C14="","",EDATE(C14,1)-1) | E14: 12-month milestone: advanced capstone + job-ready system design | F14: Pass all 8 mock interview rounds and run a structured job search. | G14: Portfolio site or GitHub profile README linking all 7 projects | H14: Mock interview scorecards, job tracker with 50+ targeted applications, referral pipeline | I14: Score >= 3/4 on every mock round. Weekly funnel review: applications, screens, onsites, offers. | J14: 70-80 | K14: Not started

Sheet Skills Matrix
A1: ID | B1: Layer | C1: Skill | D1: Month | E1: Target level | F1: Current level (0-5) | G1: Status | H1: Evidence link | I1: Project | J1: Interview ready | K1: Evidence that proves it | L1: Notes
A2: S01 | B2: Software engineering | C2: Python (functions, classes, typing, packaging) | D2: 0-1 | E2: 3 | G2: Not started | I2: P1 | J2: No | K2: CLI + API project with type hints, tests and a pyproject.toml
A3: S02 | B3: Software engineering | C3: Git and GitHub (branches, PRs, reviews) | D3: 1 | E3: 3 | G3: Not started | I3: All | J3: No | K3: Every project developed through PRs with clear commit history
A4: S03 | B4: Software engineering | C4: HTTP APIs and FastAPI | D4: 1-2 | E4: 3 | G4: Not started | I4: P1 | J4: No | K4: Documented API with validation, error handling and OpenAPI docs
A5: S04 | B5: Software engineering | C5: Async Python and concurrency | D5: 2 | E5: 3 | G5: Not started | I5: P1 | J5: No | K5: Concurrent LLM calls with timeouts, retries and rate limiting
A6: S05 | B6: Software engineering | C6: Testing (pytest, mocks, fixtures) | D6: 2 | E6: 3 | G6: Not started | I6: P1, P6 | J6: No | K6: Test suite with >70% coverage on non-LLM logic and mocked LLM calls
A7: S06 | B7: Software engineering | C7: SQL and relational databases (Postgres) | D7: 1-2 | E7: 3 | G7: Not started | I7: P2, P6 | J7: No | K7: Schema design + queries used in a project; SQL round practice
A8: S07 | B8: Software engineering | C8: Linux, shell and networking basics | D8: 1 | E8: 2 | G8: Not started | I8: P6 | J8: No | K8: Deploy and debug a service on a Linux VM over SSH
A9: S08 | B9: Software engineering | C9: Docker and docker compose | D9: 2 | E9: 3 | G9: Not started | I9: P1-P7 | J9: No | K9: Every project runs with one docker compose up
A10: S09 | B10: Software engineering | C10: CI/CD (GitHub Actions) | D10: 6 | E10: 3 | G10: Not started | I10: P6 | J10: No | K10: Pipeline running lint, tests and evals on every PR
A11: S10 | B11: Software engineering | C11: System design fundamentals | D11: 8-11 | E11: 3 | G11: Not started | I11: P7 | J11: No | K11: Written design docs for capstone; mock system design rounds passed
A12: S11 | B12: ML foundations | C12: Probability, statistics and linear algebra for ML | D12: 2-3 | E12: 2 | G12: Not started | I12: - | J12: No | K12: Explain softmax, cosine similarity, variance, confidence intervals in your own notes
A13: S12 | B13: ML foundations | C13: Supervised/unsupervised learning and evaluation metrics | D13: 2-3 | E13: 2 | G13: Not started | I13: - | J13: No | K13: Trained classifier with proper train/val/test split and metric choice justified
... A53: S52 | B53: Career | C53: Explaining trade-offs in interviews | D53: 10-12 | E53: 3 | G53: Not started | I53: - | J53: No | K53: Recorded mock interviews scored 3+/4 on rubric

Sheet Learning Tracker
A1: Month | B1: Topic | C1: Resource IDs | D1: Resource | E1: Priority | F1: Hours spent | G1: Status | H1: Start date | I1: End date | J1: Artifact produced | K1: Notes | L1: Review date
A2: 0 | B2: On-ramp: from zero to writing Python | C2: C03, C04 | D2: C03 CS50P (or C04 Python for Everybody) | E2: High | G2: Not started
A3: 0 | B3: On-ramp: from zero to writing Python | C3: C01 | D3: C01 Elements of AI (optional) | E3: High | G3: Not started
A4: 0 | B4: On-ramp: from zero to writing Python | C4: B01 | D4: B01 Python Crash Course | E4: High | G4: Not started
A5: 0 | B5: On-ramp: from zero to writing Python | C5: Y05, Y04 | D5: Y05 CodeWithHarry (Hindi) or Y04 Corey Schafer | E5: High | G5: Not started
A6: 1 | B6: Engineering foundations and your first AI app | C6: C05 | D6: C05 Missing Semester (shell, Git, debugging) | E6: High | G6: Not started
A7: 1 | B7: Engineering foundations and your first AI app | C7: C06 | D7: C06 GitHub Skills | E7: High | G7: Not started
A8: 1 | B8: Engineering foundations and your first AI app | C8: C07 | D8: C07 Kaggle SQL | E8: High | G8: Not started
A9: 1 | B9: Engineering foundations and your first AI app | C9: T04, T05 | D9: T04 Claude API docs or T05 OpenAI Cookbook | E9: High | G9: Not started
A10: 1 | B10: Engineering foundations and your first AI app | C10: C15 | D10: C15 Anthropic Academy API course | E10: High | G10: Not started
A11: 2 | B11: LLM engineering core | C11: T40 | D11: T40 FastAPI tutorial | E11: High | G11: Not started
A12: 2 | B12: LLM engineering core | C12: T41 | D12: T41 Docker get started | E12: High | G12: Not started
A13: 2 | B13: LLM engineering core | C13: T07 | D13: T07 LiteLLM | E13: High | G13: Not started
... A65: 9 | B65: AI infrastructure, advanced retrieval and capstone design | C65: B19 | D65: B19 DDIA selected chapters | E65: Medium | G65: Not started
A66: 10 | B66: Capstone build | D66: Your own design doc | E66: Medium | G66: Not started
A67: 10 | B67: Capstone build | D67: docs for chosen stack | E67: Medium | G67: Not started
A68: 10 | B68: Capstone build | C68: B22 | D68: B22 Generative AI System Design Interview (start) | E68: Medium | G68: Not started
A69: 11 | B69: Capstone production + system design preparation | C69: B22 | D69: B22 Generative AI System Design Interview | E69: Medium | G69: Not started
A70: 11 | B70: Capstone production + system design preparation | C70: B21 | D70: B21 System Design Interview (selected) | E70: Medium | G70: Not started
A71: 11 | B71: Capstone production + system design preparation | C71: Y19 | D71: Y19 ByteByteGo | E71: Medium | G71: Not started
A72: 11 | B72: Capstone production + system design preparation | D72: interview question bank (daily) | E72: Medium | G72: Not started
A73: 12 | B73: Interview sprint and job search | D73: Question bank (all categories) | E73: Medium | G73: Not started
A74: 12 | B74: Interview sprint and job search | C74: B06, B12 | D74: B06 and B12 for revision | E74: Medium | G74: Not started
A75: 12 | B75: Interview sprint and job search | D75: mock interview scripts in this playbook | E75: Medium | G75: Not started

Sheet Projects
A1: ID | B1: Project | C1: Month | D1: Objective | E1: Repo link | F1: Demo link | G1: Architecture diagram | H1: Skills demonstrated | I1: Deployment URL | J1: Evaluation report | K1: Documentation | L1: Status | M1: Interview ready | N1: Acceptance criteria
A2: P1 | B2: Production-style AI API (model comparison service) | C2: 2 | D2: Prove you can integrate foundation models like a software engineer: typed inputs and outputs, retries, tests, containers and measured trade-offs. | L2: Not started | M2: No | N2: ☐ docker compose up starts everything with only an .env file ☐ Invalid LLM JSON is caught and retried; failure returns a clear 4xx/5xx ☐ Benchmark table covers 50 examples x 3 models with accuracy, p50/p95 latency and cost ☐ Unit tests run without network (LLM calls mocked) ☐ README explains when you would choose each model
A3: P2 | B3: Evaluated RAG application | C3: 4 | D3: Show you can build retrieval that works on messy real documents and prove quality with numbers, not screenshots. | L3: Not started | M3: No | N3: ☐ Golden set of 100 questions including 15 unanswerable ones ☐ Experiment table with at least 4 configurations and recall@5, MRR, faithfulness, latency, cost ☐ Every answer shows citations that open the right source ☐ Unanswerable questions correctly refused at least 80% of the time ☐ Evaluation report explains the chosen configuration and two remaining failure modes
A4: P3 | B4: Tool-using agent | C4: 5 | D4: Show you can design an agent that is reliable, observable and safe, and justify why an agent was needed at all. | L4: Not started | M4: No | N4: ☐ Design doc explains why workflow steps vs agent steps ☐ MCP server usable from at least one other MCP client ☐ Benchmark of 20+ tasks run 5 times each with pass^1 and pass^5 ☐ Destructive tool never executes without approval (tested) ☐ Failure analysis categorizes at least 10 failed runs
A5: P4 | B5: Reusable evaluation harness | C5: 6 | D5: Demonstrate evaluation as an engineering discipline: datasets, metrics, validated judges and CI gates, reused across your projects. | L5: Not started | M5: No | N5: ☐ Harness evaluates at least two different projects (P2 and P3) ☐ LLM judge agreement with human labels reported (target >= 80%) ☐ CI blocks a PR that deliberately degrades a prompt ☐ Report shows per-category scores, not just an average ☐ Docs explain how to add a new scorer in under 30 lines
A6: P5 | B6: Multimodal system | C6: 8 | D6: Show you can handle real-world inputs that are not clean text and measure accuracy or latency where it matters. | L6: Not started | M6: No | N6: ☐ A: field-level precision/recall per field on 50+ documents; low-confidence routing to human review ☐ C: end-to-end response latency p50 and p95 with per-stage breakdown; barge-in works ☐ Cost per document or per minute of conversation reported ☐ Failure gallery with 10 annotated examples
A7: P6 | B7: Production AI service | C7: 7 | D7: Prove you can operate an AI system, not just build it: the gap most portfolios never close. | L7: Not started | M7: No | N7: ☐ Unauthenticated requests rejected; users cannot access each other's data (tested) ☐ Dashboard shows p50/p95 latency, error rate, cost per request per user ☐ Simulated provider outage handled by fallback without user-facing errors ☐ Prompt rollback demonstrated in under 5 minutes ☐ Red-team report lists attacks, results, mitigations and residual risk ☐ Monthly cost estimate at 100, 1,000 and 10,000 daily users
A8: P7 | B8: Capstone: serious domain-specific system | C8: 9-12 | D8: Create the single strongest piece of evidence in your job search and the centre of your final interview round. | L8: Not started | M8: No | N8: ☐ Passes the capstone rubric at 80% or higher ☐ Real or realistic data, not toy examples ☐ Deployed demo, 3-minute video and full documentation ☐ Defensible answers to every capstone defence question

Sheet Capstone
B1: Capstone command centre
B2: Project title:
B3: Design doc link:
A5: # | B5: Stage | C5: Questions to answer | D5: My answer / link | E5: Status
A6: 1 | B6: Problem | C6: What painful problem? How is it solved today? Success in numbers? | E6: Not started
A7: 2 | B7: Users | C7: Who exactly? What do they need? What makes them stop using it? | E7: Not started
A8: 3 | B8: Data | C8: Sources, volume, format, quality, licensing, freshness, privacy | E8: Not started
A9: 4 | B9: Architecture | C9: Components, data flow, sync vs async, where state lives | E9: Not started
A10: 5 | B10: Models | C10: Which models for which steps? Why? Fallbacks? | E10: Not started
A11: 6 | B11: Retrieval | C11: What is retrieved, how indexed, how quality is measured | E11: Not started
A12: 7 | B12: Agents / tools | C12: Workflow vs model judgment; tools and permissions | E12: Not started
A13: 8 | B13: Evaluation | C13: Datasets, metrics, human review, thresholds, regression gates | E13: Not started
A14: 9 | B14: Security | C14: Threat model, injection, authorization, data protection, audit | E14: Not started
A15: 10 | B15: Deployment | C15: Where it runs, environments, CI/CD, rollback | E15: Not started
A16: 11 | B16: Observability | C16: Traces, metrics, alerts, dashboards; debugging a bad output | E16: Not started
A17: 12 | B17: Economics | C17: Cost per task; monthly cost at 3 scales; value created | E17: Not started
... A20: 15 | B20: Documentation | C20: README, architecture, ADRs, evaluation report, runbook, limitations | E20: Not started
B23: Capstone rubric (0 / 2 / 4 per area, target 48+)
A24: # | B24: Area | C24: Score (0, 2 or 4) | D24: Evidence / what to improve
A25: 1 | B25: Problem and users
A26: 2 | B26: Data
A27: 3 | B27: Architecture
A28: 4 | B28: Model choices
A29: 5 | B29: Retrieval
A30: 6 | B30: Agents and tools
A31: 7 | B31: Evaluation
A32: 8 | B32: Security
A33: 9 | B33: Deployment
A34: 10 | B34: Observability
A35: 11 | B35: Economics
A36: 12 | B36: Failure handling
... A39: 15 | B39: Defence readiness
B40: Total | C40: =SUM(C25:C39)

Sheet Capstone Ideas
A1: ID | B1: Domain | C1: Title | D1: Difficulty | E1: Problem | F1: Users | G1: Data | H1: Workflow | I1: Techniques | J1: Evaluation | K1: Security | L1: Economics | M1: Failure modes | N1: India angle | O1: Shortlist?
A2: K01 | B2: Healthcare | C2: Clinical discharge summary copilot | D2: Advanced | E2: Doctors spend 20-40 minutes writing discharge summaries from scattered notes, labs and medication lists; errors in medication instructions cause readmissions. | F2: Resident doctors, nurses, hospital quality teams | G2: Synthea synthetic patient records (synthetichealth.github.io/synthea); openFDA drug labels (open.fda.gov); public clinical guidelines | H2: Pull patient timeline -> extract diagnoses, procedures, meds -> check drug interactions against labels -> draft summary with citations to source notes -> doctor edits and approves -> patient-friendly version in English/Hindi/Telugu | I2: Structured extraction, RAG over guidelines and labels, tool calls for interaction checks, human approval, multilingual generation | J2: Clinician-style rubric on 50 cases (completeness, correctness, citation accuracy); medication error detection recall; edit distance between draft and approved summary | K2: PHI handling, access by role, audit trail, no autonomous final output, DPDP Act-aware data handling | L2: Cost per summary vs doctor time saved | M2: Hallucinated medications, missed allergies, outdated guidelines | N2: Multilingual patient instructions; relevant to Hyderabad hospital chains and health-tech GCCs
A3: K02 | B3: Pharma / life sciences | C3: Pharmacovigilance signal triage agent | D3: Advanced | E3: Safety teams manually read thousands of adverse event reports and literature to spot drug safety signals. | F3: Drug safety scientists at pharma companies and their GCCs | G3: openFDA FAERS adverse event data (open.fda.gov); PubMed abstracts via NCBI E-utilities; public drug labels | H3: Ingest reports -> normalize drug and event terms -> cluster similar cases -> retrieve literature evidence -> draft case narrative and signal assessment -> scientist review queue | I3: Entity extraction and normalization, clustering with embeddings, agentic literature search, structured reports | J3: Term normalization accuracy; retrieval precision on 40 known drug-event pairs; reviewer agreement with triage priority | K3: Audit logs, reproducibility of every assessment, model and prompt version stamped on each output | L3: Cases triaged per hour; cost per case | M3: Wrong term mapping, missing duplicates, over-confident causality statements | N3: Hyderabad hosts major pharma GCCs (Novartis, Eli Lilly, Sanofi and others); strong local interview story
A4: K03 | B4: Legal | C4: Indian case-law research assistant | D4: Advanced | E4: Junior lawyers spend hours finding relevant precedents and statutes and often miss overruled judgments. | F4: Junior advocates, law students, in-house legal teams | G4: India Code (indiacode.nic.in) for central Acts; public Supreme Court judgment datasets (for example the Indian Supreme Court Judgments dataset on AWS Open Data) | H4: Question -> identify legal issues -> hybrid search over statutes and judgments -> citation graph check (cited, followed, overruled) -> answer memo with pinpoint citations -> lawyer verification | I4: Long-document parsing, hybrid retrieval, citation graph (GraphRAG), structured memos, refusal when evidence is weak | J4: Citation accuracy (does the paragraph say what the memo claims), recall of known leading cases on 40 questions, hallucinated citation rate (target 0) | K4: No legal advice framing, client data isolation, audit trail | L4: Research time saved per memo; retrieval cost at corpus scale | M4: Fabricated citations, overruled precedent cited as good law | N4: Large Indian legal-tech opportunity; strong demo for Bengaluru and NCR startups
A5: K04 | B5: Finance | C5: Annual report and filing analyst | D5: Advanced | E5: Analysts manually compare companies' filings to find risk changes, related-party transactions and guidance shifts. | F5: Equity research analysts, credit analysts, finance students | G5: Annual reports of listed Indian companies (BSE/NSE company pages); SEC EDGAR filings for global comparison; RBI and SEBI circulars | H5: Ingest filings with tables -> extract key metrics and risk sections -> year-over-year diff -> answer analyst questions with table citations -> generate one-page brief | I5: Table extraction, numeric validation with code execution, RAG over long documents, diffing agent | J5: Numeric extraction accuracy vs hand-checked values on 30 companies; faithfulness of risk summaries; calculation correctness | K5: Clear non-advice framing; data licensing check; prompt injection via filings | L5: Cost per company brief | M5: Unit errors (lakhs vs crores vs millions), misread tables, stale data | N5: Unit handling for Indian number formats is a real differentiator
A6: K05 | B6: Cybersecurity | C6: SOC alert triage and vulnerability prioritization agent | D6: Advanced | E6: Security operations teams face alert fatigue and cannot prioritize thousands of CVEs. | F6: SOC analysts, vulnerability management teams | G6: NVD CVE feeds (nvd.nist.gov); CISA Known Exploited Vulnerabilities catalog; MITRE ATT&CK; synthetic alert logs | H6: Alert or scan result -> enrich with CVE, KEV and ATT&CK context -> check asset inventory (tool) -> risk score with reasoning -> recommended action -> analyst approval -> ticket creation | I6: Tool-using agent, structured enrichment, retrieval over threat intel, approval gates | J6: Priority agreement with analyst labels on 100 alerts; false negative rate on known-exploited CVEs; time to triage | K6: Agent itself is a high-value target: strict tool permissions, no remediation without approval, full audit log | L6: Analyst hours saved; cost per triaged alert | M6: Missing a critical exploited vulnerability; injection via log content | N6: Hyderabad cybersecurity GCCs and MSSPs
A7: K06 | B7: Manufacturing | C7: Maintenance technician copilot | D7: Intermediate-Advanced | E7: Technicians lose time searching manuals and past work orders; knowledge leaves with senior staff. | F7: Maintenance technicians, plant engineers | G7: Public equipment manuals (PDF); synthetic maintenance logs; NASA prognostics datasets for sensor context | H7: Technician describes symptom by voice or photo -> retrieve manual sections and similar past work orders -> guided troubleshooting steps -> log resolution -> update knowledge base | I7: Multimodal input (photo of error panel), RAG over manuals, similar-case retrieval, voice interface option | J7: Correct procedure retrieval on 50 symptom scenarios; step accuracy reviewed against manuals; resolution logging completeness | K7: Safety-critical disclaimers, lockout/tagout steps never skipped, offline mode considerations | L7: Mean time to repair reduction estimate | M7: Wrong model variant manual, unsafe step ordering | N7: Relevant to Pune and Chennai manufacturing and Hyderabad aerospace/defence suppliers
A8: K07 | B8: Retail / e-commerce | C8: Multilingual product catalog and support agent | D8: Intermediate | E8: Sellers write poor product listings and support teams handle repetitive order queries in many languages. | F8: Small online sellers, e-commerce support teams | G8: Amazon Reviews 2023 dataset (McAuley Lab) for products and reviews; synthetic order database | H8: Seller uploads photos + notes -> generate listing with attributes -> quality checks. Customer query -> order lookup tool -> policy retrieval -> answer or escalate -> refund approval gate | I8: Vision-language extraction, structured attributes, support agent with tools, Indian language support | J8: Attribute accuracy on 100 products; support task success and escalation correctness on 50 scenarios; language quality review | K8: Refund fraud attempts via prompt injection; PII in chats | L8: Cost per listing and per resolved ticket vs human agent | M8: Wrong attribute claims, refunds approved outside policy | N8: Code-mixed Hinglish and regional language queries
A9: K08 | B9: Education | C9: NCERT-aligned tutor with learning diagnostics | D9: Intermediate | E9: Students need practice and explanations at their level; teachers cannot personalize for 40+ students. | F9: School students (Class 8-12), teachers | G9: NCERT textbooks (free PDFs at ncert.nic.in); previous board exam question styles (public) | H9: Student asks or takes diagnostic quiz -> retrieve chapter content -> Socratic hint rather than direct answer -> generate practice questions -> track concept mastery -> teacher dashboard | I9: RAG over textbooks, question generation with answer verification, learner model, guardrails for age-appropriate content | J9: Answer correctness on 200 textbook questions; generated question validity reviewed by a teacher; hint quality rubric | K9: Minor safety, no data selling, parental/teacher visibility | L9: Cost per student per month at scale | M9: Wrong answers stated confidently, giving away answers, syllabus drift | N9: Hindi/Telugu explanations; large market; strong for ed-tech interviews
A10: K09 | B10: Developer tools | C10: Pull request review and test generation agent | D10: Advanced | E10: Code reviews are slow and inconsistent; test coverage lags. | F10: Engineering teams | G10: Public GitHub repositories and their PR history; SWE-bench style tasks for evaluation | H10: PR opened -> fetch diff and related files -> static checks -> review comments with severity -> propose tests -> run tests in sandbox -> post summary | I10: Code retrieval, sandboxed execution, GitHub integration via MCP or API, structured review output | J10: Precision of review comments against human reviewer labels on 50 PRs; generated test pass rate and mutation score; noise rate | K10: Sandboxing, repository secrets never exposed, prompt injection via code comments | L10: Cost per PR; reviewer time saved | M10: Noisy comments, tests that pass trivially, missing real bugs | N10: Strong fit for product companies and developer-tool startups
A11: K10 | B11: Enterprise productivity | C11: Meeting-to-action workflow agent | D11: Intermediate | E11: Decisions and action items from meetings get lost; follow-ups are manual. | F11: Project managers, team leads | G11: Public meeting transcript datasets (for example AMI Meeting Corpus); synthetic Jira/Slack workspace | H11: Transcript -> extract decisions, owners, deadlines -> check existing tickets (tool) -> propose new or updated tickets -> manager approval -> post summary to team channel | I11: Structured extraction, entity resolution of people and projects, MCP connectors to ticketing and chat, approvals | J11: Action-item precision/recall on 30 labelled meetings; owner and deadline accuracy; duplicate ticket rate | K11: Permission-aware access to channels and tickets; confidential meeting handling | L11: Cost per meeting processed | M11: Wrong owner assignment, duplicate tickets, leaking private channel content | N11: Common GCC internal tooling request
A12: K11 | B12: Climate / agriculture | C12: Farmer advisory voice assistant | D12: Advanced | E12: Small farmers lack timely, local, language-appropriate advice on weather, pests and crop practices. | F12: Farmers, Krishi Vigyan Kendra staff, FPOs | G12: Open-Meteo weather API; state agriculture department and ICAR package-of-practices documents (public PDFs); crop price data from data.gov.in | H12: Farmer calls or sends voice note in Telugu/Hindi -> speech to text -> identify crop, stage, location -> weather tool + practice retrieval -> short spoken advice -> escalate to human expert for pest images or uncertain cases | I12: Voice pipeline, Indian language STT/TTS, RAG over agricultural documents, weather tools, image-based pest check (stretch) | J12: Advice correctness reviewed against documents on 60 scenarios; STT word error rate on local speech; latency | K12: No pesticide dosage without source citation; human escalation; low-literacy UX | L12: Cost per call; feasibility on low-bandwidth networks | M12: Wrong dosage, dialect misrecognition, outdated weather | N12: High social impact; aligns with state AI missions and grand challenges
A13: K12 | B13: Public sector | C13: Government scheme eligibility and application assistant | D13: Intermediate-Advanced | E13: Citizens miss benefits because scheme rules are complex and spread across portals. | F13: Citizens, Common Service Centre operators, NGOs | G13: myScheme portal (myscheme.gov.in) scheme descriptions; data.gov.in; state scheme PDFs | H13: Conversational profile collection -> rules-based eligibility check (deterministic code, not LLM) -> retrieve scheme details with citations -> document checklist -> guided application steps -> operator handoff | I13: Hybrid: LLM for conversation and extraction, deterministic rules engine for eligibility, RAG with citations, multilingual | J13: Eligibility accuracy on 100 synthetic citizen profiles vs hand-computed rules; citation correctness; task completion | K13: Minimal personal data collection, consent, no Aadhaar storage, DPDP Act-aware design | L13: Cost per citizen session at state scale | M13: Wrong eligibility decision, stale scheme rules | N13: Shows judgment: LLM where language matters, code where rules matter

Sheet GitHub
A1: Repo name | B1: Project | C1: Repo link | D1: Pinned | E1: Description + topics | F1: README complete | G1: Architecture diagram | H1: Results table | I1: CI passing | J1: Demo link | K1: Licence | L1: No secrets (scanned) | M1: Last updated | N1: Notes
B2: P1 Production-style AI API (model comparison service) | D2: No | E2: No | F2: No | G2: No | H2: No | I2: No | K2: No | L2: No
B3: P2 Evaluated RAG application | D3: No | E3: No | F3: No | G3: No | H3: No | I3: No | K3: No | L3: No
B4: P3 Tool-using agent | D4: No | E4: No | F4: No | G4: No | H4: No | I4: No | K4: No | L4: No
B5: P4 Reusable evaluation harness | D5: No | E5: No | F5: No | G5: No | H5: No | I5: No | K5: No | L5: No
B6: P5 Multimodal system | D6: No | E6: No | F6: No | G6: No | H6: No | I6: No | K6: No | L6: No
B7: P6 Production AI service | D7: No | E7: No | F7: No | G7: No | H7: No | I7: No | K7: No | L7: No
B8: P7 Capstone: serious domain-specific system | D8: No | E8: No | F8: No | G8: No | H8: No | I8: No | K8: No | L8: No
A9: profile README | B9: GitHub profile | D9: n/a | E9: No | F9: No | G9: n/a | H9: n/a | I9: n/a | K9: n/a | L9: n/a

Sheet Question Bank
A1: ID | B1: Category | C1: Difficulty | D1: Question | E1: Expected concepts | F1: Strong answer | G1: Weak answer | H1: Follow-ups and common mistakes | I1: Confidence (1-3) | J1: Last practised | K1: Next review | L1: My notes
A2: FND-01 | B2: Foundational engineering | C2: Easy | D2: What is the difference between a list and a tuple in Python, and when would you use each? | E2: mutability, hashability, intent, performance | F2: A list is mutable; a tuple is immutable. Because tuples cannot change, they are hashable when their elements are hashable, so they can be dict keys or set members (for example a cache key of `(model, prompt_hash)`). I use tuples for fixed-shape records and to signal that data should not change, and lists for collections that grow or get modified, like a batch of chunks being built. Tuples are slightly smaller and faster to create, but the main reason to choose one is intent and hashability, not speed. | G2: Tuples use round brackets and lists use square brackets; tuples are faster. | H2: • Can a tuple containing a list be used as a dict key? • When would you use a NamedTuple or dataclass instead? Common mistakes: • Claiming tuples are always deeply immutable • Choosing based only on micro-performance | K2: =IF(J2="","",J2+IF(I2=1,3,IF(I2=2,7,14)))
A3: FND-02 | B3: Foundational engineering | C3: Medium | D3: What is the GIL, and does it matter when your service makes many concurrent LLM API calls? | E3: Global Interpreter Lock, I/O-bound vs CPU-bound, asyncio, threads, multiprocessing | F3: The GIL lets only one thread execute Python bytecode at a time in CPython. It matters for CPU-bound work, but LLM API calls are I/O-bound: the thread spends most of its time waiting on the network, and the GIL is released during I/O. So asyncio or threads give real concurrency for API calls. For CPU-heavy steps such as local embedding computation, PDF parsing or tokenization at scale, I would use multiprocessing, native libraries that release the GIL, or a separate worker service. Free-threaded Python builds are emerging, but I would not design around them yet for production. | G3: The GIL makes Python single-threaded, so you need multiprocessing for concurrent API calls. | H3: • How would you cap concurrency to respect provider rate limits? • Where in a RAG ingestion pipeline is the work CPU-bound? Common mistakes: • Saying Python cannot do concurrent network calls • Using multiprocessing for pure I/O work | K3: =IF(J3="","",J3+IF(I3=1,3,IF(I3=2,7,14)))
A4: FND-03 | B4: Foundational engineering | C4: Medium | D4: You need to send 500 prompts to an LLM API as fast as possible without getting rate limited. How do you implement it? | E4: asyncio, semaphore, rate limiting, retries with backoff, batch APIs | F4: I would use an async HTTP client with `asyncio.gather` over tasks, bounded by an `asyncio.Semaphore` sized to the provider's concurrency limit, plus a token-bucket limiter for requests or tokens per minute. Each call gets a timeout and retries with exponential backoff and jitter on 429 and 5xx, honouring any `Retry-After` header. Results are written incrementally so a crash does not lose progress, and each prompt has an ID so retries are idempotent. If results are not needed immediately, I would use the provider's batch API instead, which is usually cheaper and avoids rate-limit engineering entirely. | G4: Loop through the prompts with a for loop and add time.sleep between calls. | H4: • How do you choose the semaphore size? • How would you resume after a crash halfway through? Common mistakes: • Unbounded gather causing a burst of 429s • Retrying without jitter, causing synchronized retry storms • Ignoring batch APIs for offline jobs | K4: =IF(J4="","",J4+IF(I4=1,3,IF(I4=2,7,14)))
A5: FND-04 | B5: Foundational engineering | C5: Medium | D5: Implement retry logic for an unreliable API. What should and should not be retried? | E5: exponential backoff, jitter, idempotency, retryable status codes, total timeout | F5: Retry only transient failures: timeouts, connection errors, 429 and most 5xx (500, 502, 503, 504). Do not retry 400, 401, 403, 404 or validation errors, because the same request will fail again. Use exponential backoff with full jitter, for example `sleep = random.uniform(0, base * 2**attempt)` capped at a maximum, a limited number of attempts, and an overall deadline so retries cannot exceed the user's latency budget. Honour `Retry-After` when present. Only retry non-idempotent operations such as payments or refunds if the request carries an idempotency key. Log every retry with the reason so retry-driven cost increases are visible. | G5: Wrap the call in try/except and retry three times. | H5: • Why is jitter important? • How do retries interact with LLM cost? • Where would you put a circuit breaker? Common mistakes: • Retrying 4xx errors • No overall deadline • Retrying side-effecting calls without idempotency | K5: =IF(J5="","",J5+IF(I5=1,3,IF(I5=2,7,14)))
A6: FND-05 | B6: Foundational engineering | C6: Easy | D6: What is a Python generator, and why is it useful when streaming LLM responses? | E6: yield, lazy evaluation, memory, async generators, streaming | F6: A generator is a function that uses `yield` to produce values one at a time, pausing between them, instead of building a full list in memory. For streaming LLM output, an (async) generator can yield tokens or chunks as they arrive from the provider, and a FastAPI `StreamingResponse` can forward them to the client immediately. This reduces time to first token for the user and keeps memory flat. Generators also work well for processing large document sets lazily during ingestion. | G6: A generator creates values using a for loop. | H6: • How do you handle an error that happens midway through a stream? • How would you also compute total tokens for billing while streaming? Common mistakes: • Collecting the entire stream before returning it • Forgetting async generators for async clients | K6: =IF(J6="","",J6+IF(I6=1,3,IF(I6=2,7,14)))
A7: FND-06 | B7: Foundational engineering | C7: Easy | D7: What is a decorator? Write one that measures the latency of a function. | E7: higher-order functions, functools.wraps, async support, observability | F7: A decorator is a function that takes a function and returns a wrapped version with extra behaviour. ```python import time, functools def timed(fn): @functools.wraps(fn) async def wrapper(*args, **kwargs): start = time.perf_counter() try: return await fn(*args, **kwargs) finally: logger.info('latency', extra={'fn': fn.__name__, 'ms': (time.perf_counter() - start) * 1000}) return wrapper ``` `functools.wraps` preserves the name and docstring, `perf_counter` is the right clock for durations, and `finally` records latency even on errors. In production I would emit this as a tracing span rather than a log line. | G7: A decorator is the @ symbol that adds features to a function. | H7: • How would you make it work for both sync and async functions? • How would you pass arguments to the decorator? Common mistakes: • Using time.time() for durations • Forgetting functools.wraps • Not recording failures | K7: =IF(J7="","",J7+IF(I7=1,3,IF(I7=2,7,14)))
A8: FND-07 | B8: Foundational engineering | C8: Easy | D8: What does Pydantic do, and why is it so common in AI applications? | E8: data validation, type hints, JSON Schema, structured outputs, FastAPI | F8: Pydantic validates and parses data into typed Python objects based on type hints, raising clear errors when data does not match. In AI apps it does three jobs: validating API request and response bodies (FastAPI is built on it), defining the schema for structured LLM outputs and tool arguments (Pydantic models export JSON Schema that providers accept), and validating what the model actually returned before the rest of the system trusts it. That turns 'the model returned something weird' into a caught, retryable validation error. | G8: Pydantic is a library for making classes. | H8: • What would you do when the model output fails validation twice? • How do you express an enum or constrained string? Common mistakes: • Trusting model JSON without validation • Overly permissive schemas (everything Optional[str]) | K8: =IF(J8="","",J8+IF(I8=1,3,IF(I8=2,7,14)))
A9: FND-08 | B9: Foundational engineering | C9: Easy | D9: Explain the differences between POST, PUT and PATCH. Which are idempotent? | E9: HTTP semantics, idempotency, API design | F9: POST creates a resource or triggers an action; it is not idempotent by default, so repeating it can create duplicates. PUT replaces a resource at a known URI with the full representation; repeating it leaves the same state, so it is idempotent. PATCH applies a partial update; it may or may not be idempotent depending on the operation (setting a field is, incrementing a counter is not). GET, PUT and DELETE are defined as idempotent. For AI endpoints that trigger side effects, like an agent creating a ticket, I make POST safe to retry with an idempotency key. | G9: POST adds data, PUT updates data, PATCH also updates data. | H9: • Is DELETE idempotent if the second call returns 404? • How would you design an endpoint that starts a long-running agent task? Common mistakes: • Saying PATCH is always idempotent • Using GET for actions with side effects | K9: =IF(J9="","",J9+IF(I9=1,3,IF(I9=2,7,14)))
A10: FND-09 | B10: Foundational engineering | C10: Medium | D10: Your service calls an LLM provider. For each status code, would you retry: 400, 401, 403, 404, 408, 409, 422, 429, 500, 502, 503, 504? | E10: status code semantics, transient vs permanent errors, rate limiting | F10: Retry: 408 (request timeout), 429 (rate limited, respecting Retry-After), 500, 502, 503 and 504, since they are usually transient. Do not retry: 400 and 422 (the request is malformed, for example context too long or invalid schema; fix the request instead), 401 (bad credentials), 403 (not permitted), 404 (wrong endpoint or model name). 409 depends on the API; it signals a conflict that usually needs logic, not a blind retry. For 400s caused by context length, the right reaction is to truncate or summarize context and try again deliberately, which is a different code path from a retry. | G10: Retry all errors a few times because APIs are flaky. | H10: • What would you alert on? • How do you distinguish a provider outage from your own bug? Common mistakes: • Retrying 401/403 • Treating context-length errors as transient | K10: =IF(J10="","",J10+IF(I10=1,3,IF(I10=2,7,14)))
A11: FND-10 | B11: Foundational engineering | C11: Medium | D11: How do you stream LLM tokens to a web client? Compare Server-Sent Events and WebSockets. | E11: SSE, WebSockets, chunked transfer, proxies and buffering, backpressure | F11: Server-Sent Events send a one-way stream of text events over a normal HTTP response; they are simple, work through most proxies, auto-reconnect in browsers, and fit the common case of streaming a model's answer. WebSockets give full-duplex communication, which is useful when the client also sends events mid-stream, such as interrupting a voice agent or collaborative sessions, but they need more infrastructure care. For a chat or RAG answer I use SSE via a streaming response. Practical gotchas: disable buffering in reverse proxies, send heartbeats to keep idle connections alive, and emit a final event with usage and citations so the client knows the stream finished cleanly. | G11: Use WebSockets because they are real-time. | H11: • How do you show citations that are only known at the end? • How do you handle client disconnects to stop paying for tokens? Common mistakes: • Ignoring proxy buffering • Not cancelling the upstream generation when the client disconnects | K11: =IF(J11="","",J11+IF(I11=1,3,IF(I11=2,7,14)))
A12: FND-11 | B12: Foundational engineering | C12: Medium | D12: Design a rate limiter that limits each user to 60 LLM requests per minute and 100,000 tokens per day. | E12: token bucket, sliding window, Redis, atomic operations, distributed systems | F12: I would use a token bucket per user for requests (capacity 60, refill 1 per second) and a daily token counter for usage. With multiple API instances, state must be shared, so I would store it in Redis and update it atomically with a Lua script or `INCRBY` plus expiry. Request limits are checked before calling the model. Token limits need care because output tokens are unknown upfront: reserve an estimate (input tokens plus max output tokens) before the call and reconcile with actual usage after. Return 429 with Retry-After and remaining quota headers. For fairness at scale, also add a global limiter below the provider's account limits. | G12: Keep a counter in a Python dictionary and reset it every minute. | H12: • Fixed window vs sliding window vs token bucket: trade-offs? • What happens if Redis is down? Common mistakes: • In-memory counters with multiple instances • Only counting requests when cost is driven by tokens | K12: =IF(J12="","",J12+IF(I12=1,3,IF(I12=2,7,14)))
A13: FND-12 | B13: Foundational engineering | C13: Medium | D13: What is an idempotency key and why would an AI agent need one? | E13: idempotency, retries, exactly-once effects, deduplication | F13: An idempotency key is a unique ID the client sends with a side-effecting request; the server stores the key with the result, and if the same key arrives again it returns the stored result instead of repeating the action. Agents need this because they retry: a tool call might time out after the refund was actually issued, the agent or framework retries, and without a key the customer gets two refunds. I generate the key deterministically from the task and step (for example `run_id:step:tool`), enforce it in the tool service with a unique constraint, and keep keys for longer than the maximum retry window. | G13: It is a key that makes an API secure. | H13: • Where should the key be generated, by the model or by code? • How long do you keep keys? Common mistakes: • Letting the model generate the key • Relying on 'the model will not call twice' | K13: =IF(J13="","",J13+IF(I13=1,3,IF(I13=2,7,14)))
... A301: BEH-25 | B301: Behavioural | C301: Easy | D301: Do you have any questions for us? | E301: genuine curiosity, role clarity, engineering maturity signals, team culture | F301: Ask questions that show you understand what makes AI teams succeed and help you evaluate the role: 'How do you evaluate AI features before release, and who owns evaluation?' 'What does production monitoring look like for your AI systems today?' 'What is the biggest reliability or cost challenge the team faces with its current AI features?' 'How are decisions made between building with APIs and self-hosting?' 'What would success look like for this role in the first 90 days?' 'How does the team handle AI security and data privacy reviews?' Choose two or three based on the conversation. | G301: No, I think you covered everything. | H301: • (Interviewer observes the quality of your questions) Common mistakes: • No questions • Only asking about salary or leave at this stage | K301: =IF(J301="","",J301+IF(I301=1,3,IF(I301=2,7,14)))

Sheet Mock Interviews
A1: Loop | B1: Round | C1: Date | D1: Interviewer | E1: Score 1 | F1: Score 2 | G1: Score 3 | H1: Score 4 | I1: Score 5 | J1: Score 6 | K1: Score 7 | L1: Score 8 | M1: Rubric lines scored | N1: Average | O1: What went well | P1: What to fix | Q1: Next date
A2: 1 | B2: 1 Coding | N2: =IFERROR(ROUND(AVERAGE(E2:L2),2),"")
A3: 1 | B3: 2 AI fundamentals | N3: =IFERROR(ROUND(AVERAGE(E3:L3),2),"")
A4: 1 | B4: 3 LLM and RAG | N4: =IFERROR(ROUND(AVERAGE(E4:L4),2),"")
A5: 1 | B5: 4 Agent engineering | N5: =IFERROR(ROUND(AVERAGE(E5:L5),2),"")
A6: 1 | B6: 5 System design | N6: =IFERROR(ROUND(AVERAGE(E6:L6),2),"")
A7: 1 | B7: 6 Production and debugging | N7: =IFERROR(ROUND(AVERAGE(E7:L7),2),"")
A8: 1 | B8: 7 Behavioural | N8: =IFERROR(ROUND(AVERAGE(E8:L8),2),"")
A9: 1 | B9: 8 Capstone defence | N9: =IFERROR(ROUND(AVERAGE(E9:L9),2),"")
A10: 2 | B10: 1 Coding | N10: =IFERROR(ROUND(AVERAGE(E10:L10),2),"")
A11: 2 | B11: 2 AI fundamentals | N11: =IFERROR(ROUND(AVERAGE(E11:L11),2),"")
A12: 2 | B12: 3 LLM and RAG | N12: =IFERROR(ROUND(AVERAGE(E12:L12),2),"")
A13: 2 | B13: 4 Agent engineering | N13: =IFERROR(ROUND(AVERAGE(E13:L13),2),"")
... A17: 2 | B17: 8 Capstone defence | N17: =IFERROR(ROUND(AVERAGE(E17:L17),2),"")

Sheet Job Research
A1: Title | B1: Company | C1: Company type | D1: City | E1: Seniority | F1: Years required | G1: Required skills | H1: Preferred skills | I1: Cloud | J1: Frameworks | K1: Models named | L1: Databases | M1: Infrastructure | N1: Compensation (if listed) | O1: Interview process (if public) | P1: Link | Q1: Date saved

Sheet Target Companies
A1: Company | B1: Type | C1: City | D1: Why this company | E1: AI work they do | F1: Contacts | G1: Open roles | H1: Priority | I1: Status | J1: Notes

Sheet Applications
A1: Role | B1: Company | C1: Date applied | D1: Source | E1: Job link | F1: Referral | G1: Stage | H1: Contact | I1: Next action | J1: Follow-up date | K1: Outcome / feedback | L1: Notes

Sheet Networking
A1: Name | B1: Company | C1: Role | D1: How we met | E1: Last contact | F1: Next step | G1: Next step date | H1: Referral status | I1: Notes

Sheet Weekly Review
A1: Week | B1: Week starting | C1: Shipped (links) | D1: Learned (3 concepts) | E1: Evidence added | F1: Blocked by / plan | G1: Hours actual | H1: Hours planned | I1: Energy (1-5) | J1: Next week: learn | K1: Next week: build | L1: Next week: publish
A2: 1 | B2: =IF(Dashboard!$C$7="","",Dashboard!$C$7+0) | H2: =Dashboard!$C$8
A3: 2 | B3: =IF(Dashboard!$C$7="","",Dashboard!$C$7+7) | H3: =Dashboard!$C$8
A4: 3 | B4: =IF(Dashboard!$C$7="","",Dashboard!$C$7+14) | H4: =Dashboard!$C$8
A5: 4 | B5: =IF(Dashboard!$C$7="","",Dashboard!$C$7+21) | H5: =Dashboard!$C$8
A6: 5 | B6: =IF(Dashboard!$C$7="","",Dashboard!$C$7+28) | H6: =Dashboard!$C$8
A7: 6 | B7: =IF(Dashboard!$C$7="","",Dashboard!$C$7+35) | H7: =Dashboard!$C$8
A8: 7 | B8: =IF(Dashboard!$C$7="","",Dashboard!$C$7+42) | H8: =Dashboard!$C$8
A9: 8 | B9: =IF(Dashboard!$C$7="","",Dashboard!$C$7+49) | H9: =Dashboard!$C$8
A10: 9 | B10: =IF(Dashboard!$C$7="","",Dashboard!$C$7+56) | H10: =Dashboard!$C$8
A11: 10 | B11: =IF(Dashboard!$C$7="","",Dashboard!$C$7+63) | H11: =Dashboard!$C$8
A12: 11 | B12: =IF(Dashboard!$C$7="","",Dashboard!$C$7+70) | H12: =Dashboard!$C$8
A13: 12 | B13: =IF(Dashboard!$C$7="","",Dashboard!$C$7+77) | H13: =Dashboard!$C$8
A14: 13 | B14: =IF(Dashboard!$C$7="","",Dashboard!$C$7+84) | H14: =Dashboard!$C$8
A15: 14 | B15: =IF(Dashboard!$C$7="","",Dashboard!$C$7+91) | H15: =Dashboard!$C$8
A16: 15 | B16: =IF(Dashboard!$C$7="","",Dashboard!$C$7+98) | H16: =Dashboard!$C$8
A17: 16 | B17: =IF(Dashboard!$C$7="","",Dashboard!$C$7+105) | H17: =Dashboard!$C$8
A18: 17 | B18: =IF(Dashboard!$C$7="","",Dashboard!$C$7+112) | H18: =Dashboard!$C$8
A19: 18 | B19: =IF(Dashboard!$C$7="","",Dashboard!$C$7+119) | H19: =Dashboard!$C$8
A20: 19 | B20: =IF(Dashboard!$C$7="","",Dashboard!$C$7+126) | H20: =Dashboard!$C$8
A21: 20 | B21: =IF(Dashboard!$C$7="","",Dashboard!$C$7+133) | H21: =Dashboard!$C$8
A22: 21 | B22: =IF(Dashboard!$C$7="","",Dashboard!$C$7+140) | H22: =Dashboard!$C$8
A23: 22 | B23: =IF(Dashboard!$C$7="","",Dashboard!$C$7+147) | H23: =Dashboard!$C$8
A24: 23 | B24: =IF(Dashboard!$C$7="","",Dashboard!$C$7+154) | H24: =Dashboard!$C$8
A25: 24 | B25: =IF(Dashboard!$C$7="","",Dashboard!$C$7+161) | H25: =Dashboard!$C$8
A26: 25 | B26: =IF(Dashboard!$C$7="","",Dashboard!$C$7+168) | H26: =Dashboard!$C$8
A27: 26 | B27: =IF(Dashboard!$C$7="","",Dashboard!$C$7+175) | H27: =Dashboard!$C$8
A28: 27 | B28: =IF(Dashboard!$C$7="","",Dashboard!$C$7+182) | H28: =Dashboard!$C$8
A29: 28 | B29: =IF(Dashboard!$C$7="","",Dashboard!$C$7+189) | H29: =Dashboard!$C$8
A30: 29 | B30: =IF(Dashboard!$C$7="","",Dashboard!$C$7+196) | H30: =Dashboard!$C$8
A31: 30 | B31: =IF(Dashboard!$C$7="","",Dashboard!$C$7+203) | H31: =Dashboard!$C$8
A32: 31 | B32: =IF(Dashboard!$C$7="","",Dashboard!$C$7+210) | H32: =Dashboard!$C$8
A33: 32 | B33: =IF(Dashboard!$C$7="","",Dashboard!$C$7+217) | H33: =Dashboard!$C$8
A34: 33 | B34: =IF(Dashboard!$C$7="","",Dashboard!$C$7+224) | H34: =Dashboard!$C$8
A35: 34 | B35: =IF(Dashboard!$C$7="","",Dashboard!$C$7+231) | H35: =Dashboard!$C$8
A36: 35 | B36: =IF(Dashboard!$C$7="","",Dashboard!$C$7+238) | H36: =Dashboard!$C$8
A37: 36 | B37: =IF(Dashboard!$C$7="","",Dashboard!$C$7+245) | H37: =Dashboard!$C$8
A38: 37 | B38: =IF(Dashboard!$C$7="","",Dashboard!$C$7+252) | H38: =Dashboard!$C$8
A39: 38 | B39: =IF(Dashboard!$C$7="","",Dashboard!$C$7+259) | H39: =Dashboard!$C$8
A40: 39 | B40: =IF(Dashboard!$C$7="","",Dashboard!$C$7+266) | H40: =Dashboard!$C$8
A41: 40 | B41: =IF(Dashboard!$C$7="","",Dashboard!$C$7+273) | H41: =Dashboard!$C$8
A42: 41 | B42: =IF(Dashboard!$C$7="","",Dashboard!$C$7+280) | H42: =Dashboard!$C$8
A43: 42 | B43: =IF(Dashboard!$C$7="","",Dashboard!$C$7+287) | H43: =Dashboard!$C$8
A44: 43 | B44: =IF(Dashboard!$C$7="","",Dashboard!$C$7+294) | H44: =Dashboard!$C$8
A45: 44 | B45: =IF(Dashboard!$C$7="","",Dashboard!$C$7+301) | H45: =Dashboard!$C$8
A46: 45 | B46: =IF(Dashboard!$C$7="","",Dashboard!$C$7+308) | H46: =Dashboard!$C$8
A47: 46 | B47: =IF(Dashboard!$C$7="","",Dashboard!$C$7+315) | H47: =Dashboard!$C$8
A48: 47 | B48: =IF(Dashboard!$C$7="","",Dashboard!$C$7+322) | H48: =Dashboard!$C$8
A49: 48 | B49: =IF(Dashboard!$C$7="","",Dashboard!$C$7+329) | H49: =Dashboard!$C$8
A50: 49 | B50: =IF(Dashboard!$C$7="","",Dashboard!$C$7+336) | H50: =Dashboard!$C$8
A51: 50 | B51: =IF(Dashboard!$C$7="","",Dashboard!$C$7+343) | H51: =Dashboard!$C$8
A52: 51 | B52: =IF(Dashboard!$C$7="","",Dashboard!$C$7+350) | H52: =Dashboard!$C$8
A53: 52 | B53: =IF(Dashboard!$C$7="","",Dashboard!$C$7+357) | H53: =Dashboard!$C$8

Sheet Monthly Review
A1: Month | B1: Theme | C1: Build | D1: Understand | E1: Evaluate | F1: Ship | G1: Communicate | H1: Interview | I1: Average | J1: Skills moved (with evidence) | K1: Project status | L1: Job research insights | M1: Questions I struggled with | N1: Decision | O1: One thing to stop doing
A2: 0 | B2: On-ramp: from zero to writing Python | I2: =IFERROR(ROUND(AVERAGE(C2:H2),2),"")
A3: 1 | B3: Engineering foundations and your first AI app | I3: =IFERROR(ROUND(AVERAGE(C3:H3),2),"")
A4: 2 | B4: LLM engineering core | I4: =IFERROR(ROUND(AVERAGE(C4:H4),2),"")
A5: 3 | B5: How LLMs actually work | I5: =IFERROR(ROUND(AVERAGE(C5:H5),2),"")
A6: 4 | B6: Retrieval-augmented generation | I6: =IFERROR(ROUND(AVERAGE(C6:H6),2),"")
A7: 5 | B7: Agents, tools and MCP | I7: =IFERROR(ROUND(AVERAGE(C7:H7),2),"")
A8: 6 | B8: Evaluation as an engineering system | I8: =IFERROR(ROUND(AVERAGE(C8:H8),2),"")
A9: 7 | B9: Production hardening and AI security | I9: =IFERROR(ROUND(AVERAGE(C9:H9),2),"")
A10: 8 | B10: Multimodal AI and fine-tuning | I10: =IFERROR(ROUND(AVERAGE(C10:H10),2),"")
A11: 9 | B11: AI infrastructure, advanced retrieval and capstone design | I11: =IFERROR(ROUND(AVERAGE(C11:H11),2),"")
A12: 10 | B12: Capstone build | I12: =IFERROR(ROUND(AVERAGE(C12:H12),2),"")
A13: 11 | B13: Capstone production + system design preparation | I13: =IFERROR(ROUND(AVERAGE(C13:H13),2),"")
A14: 12 | B14: Interview sprint and job search | I14: =IFERROR(ROUND(AVERAGE(C14:H14),2),"")

Sheet Courses
A1: ID | B1: Stage | C1: Course | D1: Provider | E1: Instructor | F1: Link | G1: Price | H1: Free option | I1: Duration | J1: Level | K1: Prerequisites | L1: Hands-on (1-5) | M1: Depth (1-5) | N1: Project | O1: Certificate | P1: Career relevance | Q1: Recommendation | R1: Best for | S1: My status | T1: My notes
A2: C01 | B2: 0. AI literacy | C2: Elements of AI | D2: University of Helsinki & MinnaLearn | E2: Teemu Roos and team | F2: https://www.elementsofai.com/ | G2: Free | H2: Fully free | I2: ~30 hours | J2: Absolute beginner | K2: None | L2: 1 | M2: 2 | N2: None (quizzes and short exercises) | O2: Free certificate | P2: Builds vocabulary for non-tech learners before touching code | Q2: Take if you have zero tech background. Skip if you already code. | R2: Non-tech | S2: Not started
A3: C02 | B3: 0. AI literacy | C3: AI for Everyone | D3: DeepLearning.AI (Coursera) | E3: Andrew Ng | F3: https://www.coursera.org/learn/ai-for-everyone | G3: Coursera pricing (varies by region) | H3: Financial aid available; preview content free | I3: ~6 hours | J3: Absolute beginner | K3: None | L3: 1 | M3: 1 | N3: None | O3: Paid certificate | P3: Helps non-tech and management learners understand what AI projects look like | Q3: Optional. Watch in a weekend, then move to Python. | R3: Non-tech, Product | S3: Not started
A4: C03 | B4: 1. Programming | C4: CS50's Introduction to Programming with Python (CS50P) | D4: Harvard University (edX / cs50.harvard.edu) | E4: David J. Malan | F4: https://cs50.harvard.edu/python/ | G4: Free | H4: Fully free; paid verified certificate on edX | I4: ~10 weeks at 6-8 h/week | J4: Beginner | K4: None | L4: 5 | M4: 4 | N4: Final project of your choice | O4: Free CS50 certificate; paid edX certificate | P4: The best structured Python start for students and career switchers | Q4: Start here if you cannot write Python yet. | R4: Non-tech, Beginner | S4: Not started
A5: C04 | B5: 1. Programming | C5: Python for Everybody | D5: University of Michigan / py4e.com | E5: Charles Severance | F5: https://www.py4e.com/ | G5: Free | H5: Fully free | I5: ~8 weeks | J5: Beginner | K5: None | L5: 4 | M5: 2 | N5: Data retrieval and database exercises | O5: Free badges on py4e.com | P5: Gentler than CS50P; strong on files, web data and SQLite | Q5: Alternative to CS50P if you want a slower pace. | R5: Non-tech, Beginner | S5: Not started
A6: C05 | B6: 1. Programming | C6: The Missing Semester of Your CS Education | D6: MIT | E6: Anish Athalye, Jon Gjengset, Jose Javier Gonzalez Ortiz | F6: https://missing.csail.mit.edu/ | G6: Free | H6: Fully free | I6: ~12 hours | J6: Beginner to intermediate | K6: Basic programming | L6: 5 | M6: 3 | N6: Shell, Git, debugging exercises | O6: None | P6: Terminal, Git, editors and debugging: the skills tutorials assume you have | Q6: Do it in Month 1. Most self-taught learners skip this and pay later. | R6: All | S6: Not started
A7: C06 | B7: 1. Programming | C7: GitHub Skills | D7: GitHub | E7: GitHub | F7: https://skills.github.com/ | G7: Free | H7: Fully free | I7: 1-2 hours per module | J7: Beginner | K7: GitHub account | L7: 5 | M7: 2 | N7: Interactive repos (PRs, Actions, Pages) | O7: None | P7: Git, pull requests and GitHub Actions used in every project in this playbook | Q7: Do 'Introduction to GitHub' and 'Hello GitHub Actions'. | R7: All | S7: Not started
A8: C07 | B8: 1. Programming | C8: Kaggle Learn: Intro to SQL + Advanced SQL | D8: Kaggle | E8: Kaggle team | F8: https://www.kaggle.com/learn | G8: Free | H8: Fully free | I8: ~8 hours | J8: Beginner | K8: None | L8: 4 | M8: 2 | N8: BigQuery exercises | O8: Free certificate | P8: SQL shows up in coding rounds and in almost every real AI data pipeline | Q8: Do both SQL micro-courses. Also useful: Pandas. | R8: All | S8: Not started
A9: C08 | B9: 2. ML foundations | C9: Mathematics for Machine Learning and Data Science Specialization | D9: DeepLearning.AI (Coursera) | E9: Luis Serrano | F9: https://www.coursera.org/specializations/mathematics-for-machine-learning-and-data-science | G9: Coursera pricing (varies by region) | H9: Financial aid available | I9: ~3 months at 5 h/week | J9: Beginner | K9: High-school math | L9: 3 | M9: 3 | N9: Python labs | O9: Paid certificate | P9: Linear algebra, calculus and probability explained visually with code | Q9: Take if math blocks you. Otherwise use 3Blue1Brown + StatQuest. | R9: Non-tech, Beginner | S9: Not started
A10: C09 | B10: 2. ML foundations | C10: Machine Learning Crash Course | D10: Google for Developers | E10: Google engineers | F10: https://developers.google.com/machine-learning/crash-course | G10: Free | H10: Fully free | I10: ~15 hours | J10: Beginner | K10: Python, basic algebra | L10: 3 | M10: 3 | N10: Colab exercises | O10: Free completion badge | P10: Fast, updated overview including LLM and production ML modules | Q10: The fastest credible ML overview. Good for software engineers. | R10: Beginner, SWE | S10: Not started
A11: C10 | B11: 2. ML foundations | C11: Machine Learning Specialization | D11: DeepLearning.AI & Stanford (Coursera) | E11: Andrew Ng | F11: https://www.coursera.org/specializations/machine-learning-introduction | G11: Coursera pricing (varies by region) | H11: Financial aid available | I11: ~2.5 months at 9 h/week | J11: Beginner | K11: Python, high-school math | L11: 3 | M11: 4 | N11: Labs (regression, classification, recommenders) | O11: Paid certificate | P11: Classic ML intuition: loss, gradient descent, overfitting, evaluation | Q11: Recommended for students and data-curious beginners. | R11: Beginner, Data Scientist | S11: Not started
A12: C11 | B12: 2. ML foundations | C12: Practical Deep Learning for Coders | D12: fast.ai | E12: Jeremy Howard | F12: https://course.fast.ai/ | G12: Free | H12: Fully free | I12: ~9 lessons, 60-90 hours with practice | J12: Intermediate | K12: 1 year of coding | L12: 5 | M12: 4 | N12: Train and deploy real models | O12: None | P12: Top-down, code-first deep learning; excellent for software engineers | Q12: Best free deep learning course for people who learn by building. | R12: SWE, Data Scientist | S12: Not started
A13: C12 | B13: 2. ML foundations | C13: Neural Networks: Zero to Hero | D13: Andrej Karpathy (YouTube + GitHub) | E13: Andrej Karpathy | F13: https://karpathy.ai/zero-to-hero.html | G13: Free | H13: Fully free | I13: ~20 hours of video, 60+ hours coding along | J13: Intermediate | K13: Python, basic calculus | L13: 5 | M13: 5 | N13: Build micrograd, makemore and a GPT from scratch | O13: None | P13: The clearest path to actually understanding how transformers and training work | Q13: Must do for every engineering track. Code along, do not just watch. | R13: All engineering tracks | S13: Not started
... A31: C30 | B31: India options | C31: NPTEL: Introduction to Machine Learning | D31: IIT Madras (NPTEL / SWAYAM) | E31: Prof. Balaraman Ravindran | F31: https://onlinecourses.nptel.ac.in/ | G31: Free to learn; paid proctored exam | H31: All lectures and assignments free | I31: 12 weeks | J31: Intermediate | K31: Probability, linear algebra | L31: 2 | M31: 4 | N31: Weekly assignments | O31: IIT-branded certificate after proctored exam | P31: Credible, low-cost option for Indian college students; some universities give credits | Q31: Good for students who want an IIT certificate on the CV. Pair it with projects. | R31: College students (India) | S31: Not started

Sheet Tutorials
A1: ID | B1: Skill | C1: Tutorial | D1: Source | E1: Link | F1: Prerequisites | G1: Time | H1: Output you should have | I1: Difficulty | J1: Production relevance | K1: My status | L1: My notes
A2: T01 | B2: Transformers intuition | C2: The Illustrated Transformer | D2: Jay Alammar | E2: https://jalammar.github.io/illustrated-transformer/ | F2: Basic neural networks | G2: 2 hours | H2: Draw the attention flow from memory | I2: Beginner | J2: Low (conceptual), essential for interviews | K2: Not started
A3: T02 | B3: Build a GPT from scratch | C3: nanoGPT | D3: Andrej Karpathy (GitHub) | E3: https://github.com/karpathy/nanoGPT | F3: PyTorch basics | G3: 8-12 hours | H3: Train a small character-level GPT | I3: Intermediate | J3: Low, high for understanding | K3: Not started
A4: T03 | B4: Full LLM pipeline | C4: nanochat | D4: Andrej Karpathy (GitHub) | E4: https://github.com/karpathy/nanochat | F4: nanoGPT, cloud GPU access | G4: 15-25 hours | H4: Tokenizer, pretraining, fine-tuning and a chat UI end to end | I4: Advanced | J4: Medium for Research/Infra tracks | K4: Not started
A5: T04 | B5: LLM API usage | C5: Claude API documentation | D5: Anthropic | E5: https://docs.claude.com/ | F5: Python, HTTP | G5: 4 hours | H5: Streaming chat, tool use, structured output | I5: Beginner | J5: High | K5: Not started
A6: T05 | B6: LLM API patterns | C6: OpenAI Cookbook | D6: OpenAI | E6: https://cookbook.openai.com/ | F6: Python | G6: Pick 3-4 recipes, 1 hour each | H6: Working notebooks for embeddings, function calling, evals | I6: Beginner to intermediate | J6: High | K6: Not started
A7: T06 | B7: Multimodal and long context | C7: Gemini API Cookbook | D7: Google (GitHub) | E7: https://github.com/google-gemini/cookbook | F7: Python | G7: 4-6 hours | H7: Video, PDF and audio understanding examples | I7: Beginner to intermediate | J7: High | K7: Not started
A8: T07 | B8: Model gateway | C8: LiteLLM | D8: BerriAI (docs) | E8: https://docs.litellm.ai/ | F8: Python, one LLM API | G8: 3 hours | H8: One interface to multiple providers with fallbacks and cost logging | I8: Intermediate | J8: High | K8: Not started
A9: T08 | B9: Agent design principles | C9: Building effective agents | D9: Anthropic Engineering | E9: https://www.anthropic.com/engineering/building-effective-agents | F9: LLM API basics | G9: 1 hour | H9: Decide workflow vs agent for your use case | I9: Beginner | J9: High | K9: Not started
A10: T09 | B10: Context engineering | C10: Effective context engineering for AI agents | D10: Anthropic Engineering | E10: https://www.anthropic.com/engineering/effective-context-engineering-for-ai-agents | F10: Built one agent | G10: 1 hour | H10: A context budget plan for your agent | I10: Intermediate | J10: High | K10: Not started
A11: T10 | B11: RAG retrieval quality | C11: Introducing Contextual Retrieval | D11: Anthropic | E11: https://www.anthropic.com/news/contextual-retrieval | F11: Basic RAG | G11: 1 hour read + 4 hours to reproduce | H11: Before/after retrieval metrics on your dataset | I11: Intermediate | J11: High | K11: Not started
A12: T11 | B12: Agent overview | C12: LLM Powered Autonomous Agents | D12: Lilian Weng | E12: https://lilianweng.github.io/posts/2023-06-23-agent/ | F12: LLM basics | G12: 2 hours | H12: Map planning, memory and tool use components | I12: Intermediate | J12: Medium (foundational) | K12: Not started
A13: T12 | B13: LLM system patterns | C13: Patterns for Building LLM-based Systems & Products | D13: Eugene Yan | E13: https://eugeneyan.com/writing/llm-patterns/ | F13: Built one LLM app | G13: 2 hours | H13: Pattern checklist for your project design doc | I13: Intermediate | J13: High | K13: Not started
... A51: T50 | B51: AI Anytime project walkthroughs | C51: AI Anytime GitHub repositories | D51: AI Anytime | E51: https://github.com/AIAnytime | F51: Python | G51: Varies | H51: Reference implementations of RAG, agents, multimodal and local LLM apps | I51: Beginner to advanced | J51: Medium to high | K51: Not started

Sheet YouTube
A1: ID | B1: Category | C1: Channel | D1: Link | E1: Language | F1: Best for | G1: Start with | H1: Accuracy | I1: Depth | J1: Practical | K1: Consistency | L1: Relevance | M1: My status | N1: My notes
A2: Y01 | B2: Foundations | C2: 3Blue1Brown | D2: https://www.youtube.com/@3blue1brown | E2: English | F2: Linear algebra, calculus and neural network intuition | G2: Essence of Linear Algebra; Neural Networks series (includes transformers and attention) | H2: 5 | I2: 4 | J2: 2 | K2: 4 | L2: 4 | M2: Not started
A3: Y02 | B3: Foundations | C3: StatQuest with Josh Starmer | D3: https://www.youtube.com/@statquest | E3: English | F3: Statistics and classical ML explained slowly and clearly | G3: Statistics Fundamentals; Machine Learning playlist | H3: 5 | I3: 3 | J3: 2 | K3: 5 | L3: 4 | M3: Not started
A4: Y03 | B4: Foundations | C4: Andrej Karpathy | D4: https://www.youtube.com/@AndrejKarpathy | E4: English | F4: Building neural networks and GPTs from scratch; LLM mental models | G4: Let's build GPT: from scratch, in code, spelled out; Deep Dive into LLMs like ChatGPT | H4: 5 | I4: 5 | J4: 5 | K4: 3 | L4: 5 | M4: Not started
A5: Y04 | B5: Foundations | C5: Corey Schafer | D5: https://www.youtube.com/@coreyms | E5: English | F5: Python fundamentals done properly | G5: Python Programming Beginner Tutorials playlist | H5: 5 | I5: 3 | J5: 4 | K5: 3 | L5: 3 | M5: Not started
A6: Y05 | B6: Foundations (Hindi) | C6: CodeWithHarry | D6: https://www.youtube.com/@CodeWithHarry | E6: Hindi | F6: Absolute beginners in India who prefer Hindi explanations | G6: Python course for beginners | H6: 4 | I6: 2 | J6: 4 | K6: 5 | L6: 3 | M6: Not started
A7: Y06 | B7: ML and DL (Hindi) | C7: CampusX | D7: https://www.youtube.com/@campusx-official | E7: Hindi | F7: Structured ML and deep learning playlists in Hindi with depth | G7: 100 Days of Machine Learning; 100 Days of Deep Learning | H7: 4 | I7: 4 | J7: 4 | K7: 4 | L7: 4 | M7: Not started
A8: Y07 | B8: LLM internals | C8: Umar Jamil | D8: https://www.youtube.com/@umarjamilai | E8: English | F8: Paper-to-code implementations: transformers, LLaMA, RLHF, quantization | G8: Coding a Transformer from scratch on PyTorch | H8: 5 | I8: 5 | J8: 5 | K8: 3 | L8: 5 | M8: Not started
A9: Y08 | B9: LLM internals | C9: Welch Labs | D9: https://www.youtube.com/@WelchLabs | E9: English | F9: Visual explanations of how models actually compute | G9: Videos on attention and model internals | H9: 5 | I9: 4 | J9: 1 | K9: 3 | L9: 4 | M9: Not started
A10: Y09 | B10: LLM engineering | C10: AI Anytime | D10: https://www.youtube.com/@AIAnytime | E10: English | F10: Project-based builds: RAG, agents, local LLMs, multimodal and production apps with open-source code | G10: Pick the video matching your current project in this playbook | H10: 4 | I10: 4 | J10: 5 | K10: 5 | L10: 5 | M10: Not started
A11: Y10 | B11: LLM engineering | C11: Sam Witteveen | D11: https://www.youtube.com/@samwitteveenai | E11: English | F11: Hands-on walkthroughs of new models, frameworks and agent tooling | G11: Recent videos on agent frameworks | H11: 4 | I11: 3 | J11: 4 | K11: 5 | L11: 5 | M11: Not started
A12: Y11 | B12: LLM engineering | C12: Dave Ebbelaar | D12: https://www.youtube.com/@daveebbelaar | E12: English | F12: Pragmatic AI engineering for real client projects, minimal framework bloat | G12: Building AI agents in pure Python | H12: 4 | I12: 3 | J12: 5 | K12: 4 | L12: 5 | M12: Not started
A13: Y12 | B13: LLM engineering | C13: Trelis Research | D13: https://www.youtube.com/@TrelisResearch | E13: English | F13: Fine-tuning, inference, evaluation experiments with numbers | G13: Fine-tuning and inference serving videos | H13: 4 | I13: 5 | J13: 5 | K13: 4 | L13: 4 | M13: Not started
... A23: Y22 | B23: Foundations | C23: freeCodeCamp.org | D23: https://www.youtube.com/@freecodecamp | E23: English | F23: Long-form full courses on Python, SQL, Docker, Linux | G23: Search the exact skill you are missing this month | H23: 4 | I23: 3 | J23: 4 | K23: 5 | L23: 3 | M23: Not started

Sheet Books
A1: ID | B1: Group | C1: Title | D1: Authors | E1: Year | F1: How to read | G1: Why it is here | H1: When | I1: Tracks | J1: My status | K1: Chapters read | L1: My notes
A2: B01 | B2: Fundamentals | C2: Python Crash Course (3rd edition) | D2: Eric Matthes | E2: 2023 | F2: Read fully | G2: Cleanest book path from zero to writing real Python projects | H2: Month 0-1 | I2: Non-tech, Beginner | J2: Not started
A3: B02 | B3: Fundamentals | C3: Fluent Python (2nd edition) | D3: Luciano Ramalho | E3: 2022 | F3: Reference only | G3: Idiomatic Python: data model, generators, async, typing | H3: Month 3 onward, when your code works but looks junior | I3: SWE, all | J3: Not started
A4: B03 | B4: Fundamentals | C4: Architecture Patterns with Python | D4: Harry Percival, Bob Gregory | E4: 2020 | F4: Selected chapters | G4: Repository pattern, service layer, testing boundaries: how to keep AI apps maintainable | H4: Month 6 | I4: Beginner, Data Scientist | J4: Not started
A5: B04 | B5: ML | C5: Hands-On Machine Learning with Scikit-Learn and PyTorch | D5: Aurélien Géron | E5: 2025 | F5: Selected chapters | G5: The practical ML book most engineers learn from; now with a PyTorch edition | H5: Month 2-3 | I5: Beginner, SWE | J5: Not started
A6: B05 | B6: ML | C6: Mathematics for Machine Learning | D6: Marc Peter Deisenroth, A. Aldo Faisal, Cheng Soon Ong | E6: 2020 | F6: Selected chapters | G6: Free PDF covering exactly the linear algebra and probability ML uses | H6: When math blocks you | I6: Research, Data Scientist | J6: Not started
A7: B06 | B7: ML | C7: The Hundred-Page Machine Learning Book | D7: Andriy Burkov | E7: 2019 | F7: Read fully | G7: Compact revision of classical ML before interviews | H7: Month 10-11 (interview prep) | I7: All | J7: Not started
A8: B07 | B8: Deep learning | C8: Understanding Deep Learning | D8: Simon J. D. Prince | E8: 2023 | F8: Selected chapters | G8: Modern, well-illustrated, free online; strong on transformers and diffusion | H8: Month 3 | I8: ML Engineer, Research | J8: Not started
A9: B08 | B9: Deep learning | C9: Deep Learning with Python (3rd edition) | D9: François Chollet, Matthew Watson | E9: 2025 | F9: Selected chapters | G9: Intuition-first deep learning with modern generative AI chapters | H9: Month 3 | I9: Beginner, Data Scientist | J9: Not started
A10: B09 | B10: Deep learning | C10: Deep Learning | D10: Ian Goodfellow, Yoshua Bengio, Aaron Courville | E10: 2016 | F10: Reference only | G10: Theory reference for optimization and regularization questions | H10: As needed | I10: Research | J10: Not started
A11: B10 | B11: LLMs | C11: Hands-On Large Language Models | D11: Jay Alammar, Maarten Grootendorst | E11: 2024 | F11: Read fully | G11: Visual, code-first tour of tokens, embeddings, semantic search, RAG and fine-tuning | H11: Month 3-4 | I11: All engineering tracks | J11: Not started
A12: B11 | B12: LLMs | C12: Build a Large Language Model (From Scratch) | D12: Sebastian Raschka | E12: 2024 | F12: Read fully | G12: Implement a GPT-style model step by step; removes the magic | H12: Month 3-4 (or Month 7 for Beginner track) | I12: ML Engineer, Research, SWE | J12: Not started
A13: B12 | B13: LLMs | C13: The Hundred-Page Language Models Book | D13: Andriy Burkov | E13: 2025 | F13: Read fully | G13: Short, rigorous LLM refresher with code | H13: Month 10 (revision) | I13: All | J13: Not started
... A30: B29 | B30: Infrastructure | C30: Programming Massively Parallel Processors (4th edition) | D30: Wen-mei W. Hwu, David B. Kirk, Izzat El Hajj | E30: 2022 | F30: Selected chapters | G30: CUDA and GPU parallelism fundamentals | H30: Infra track | I30: Infra, Research | J30: Not started

Sheet Papers
A1: ID | B1: Tier | C1: Title | D1: Authors | E1: Year | F1: Link | G1: Why it matters | H1: Prerequisites | I1: Reproduction exercise | J1: My status | K1: Exercise done | L1: 5-bullet summary
A2: P01 | B2: Must-read | C2: Attention Is All You Need | D2: Vaswani et al. | E2: 2017 | F2: https://arxiv.org/abs/1706.03762 | G2: Introduces the transformer. Every LLM question in interviews traces back here. | H2: Matrix multiplication, softmax, basic neural networks | I2: Implement scaled dot-product and multi-head attention in PyTorch; verify shapes and a causal mask with unit tests. | J2: Not started | K2: No
A3: P02 | B3: Must-read | C3: Language Models are Few-Shot Learners (GPT-3) | D3: Brown et al. | E3: 2020 | F3: https://arxiv.org/abs/2005.14165 | G3: Shows in-context learning emerging with scale; the basis of prompting as an interface. | H3: P01 | I3: Measure zero-shot vs 3-shot vs 10-shot accuracy of a small open model on 100 classification examples and plot the curve. | J3: Not started | K3: No
A4: P03 | B4: Must-read | C4: Training language models to follow instructions with human feedback (InstructGPT) | D4: Ouyang et al. | E4: 2022 | F4: https://arxiv.org/abs/2203.02155 | G4: Explains SFT + reward model + RLHF, the recipe that made chat models useful. | H4: P02, basic reinforcement learning vocabulary | I4: Draw the three-stage pipeline and explain in 5 sentences why a 1.3B aligned model beat a 175B base model on human preference. | J4: Not started | K4: No
A5: P04 | B5: Must-read | C5: Retrieval-Augmented Generation for Knowledge-Intensive NLP Tasks | D5: Lewis et al. | E5: 2020 | F5: https://arxiv.org/abs/2005.11401 | G5: The original RAG formulation. Know what it actually proposed versus what the industry now calls RAG. | H5: Embeddings, P01 | I5: Build a 50-line retrieve-then-generate baseline over 200 Wikipedia paragraphs and report exact-match on 50 questions with and without retrieval. | J5: Not started | K5: No
A6: P05 | B6: Must-read | C6: ReAct: Synergizing Reasoning and Acting in Language Models | D6: Yao et al. | E6: 2022 | F6: https://arxiv.org/abs/2210.03629 | G6: The reason-act-observe loop behind most tool-using agents. | H6: Prompting, tool calling | I6: Write a ReAct loop without any framework using two tools (search, calculator); log every thought/action/observation and count failure types on 30 tasks. | J6: Not started | K6: No
A7: P06 | B7: Must-read | C7: LoRA: Low-Rank Adaptation of Large Language Models | D7: Hu et al. | E7: 2021 | F7: https://arxiv.org/abs/2106.09685 | G7: The default way to fine-tune cheaply; interviewers ask how rank and target modules affect results. | H7: Linear algebra (matrix rank), fine-tuning basics | I7: Fine-tune a small model with LoRA ranks 4, 16 and 64; compare trainable parameters, VRAM and eval score in one table. | J7: Not started | K7: No
A8: P07 | B8: Must-read | C8: Efficient Memory Management for Large Language Model Serving with PagedAttention (vLLM) | D8: Kwon et al. | E8: 2023 | F8: https://arxiv.org/abs/2309.06180 | G8: Explains the KV cache memory problem and why modern serving engines batch so efficiently. | H8: P01, KV cache concept | I8: Serve the same model with Hugging Face generate and vLLM; benchmark throughput at 1, 8 and 32 concurrent requests. | J8: Not started | K8: No
A9: P08 | B9: Must-read | C9: Lost in the Middle: How Language Models Use Long Contexts | D9: Liu et al. | E9: 2023 | F9: https://arxiv.org/abs/2307.03172 | G9: Proves that more context is not free. Foundation of context engineering decisions. | H9: RAG basics | I9: Place the answer passage at positions 1, 10 and 20 of a 20-passage prompt for a current model; plot accuracy by position. | J9: Not started | K9: No
A10: P09 | B10: Must-read | C10: Judging LLM-as-a-Judge with MT-Bench and Chatbot Arena | D10: Zheng et al. | E10: 2023 | F10: https://arxiv.org/abs/2306.05685 | G10: Documents position, verbosity and self-enhancement bias in LLM judges. Required before trusting any automated eval. | H10: Evaluation basics | I10: Run an LLM judge on 40 answer pairs in both orders; measure how often the verdict flips when you swap positions. | J10: Not started | K10: No
A11: P10 | B11: Must-read | C11: Not what you've signed up for: Compromising Real-World LLM-Integrated Applications with Indirect Prompt Injection | D11: Greshake et al. | E11: 2023 | F11: https://arxiv.org/abs/2302.12173 | G11: Defines indirect prompt injection, the most important security threat for RAG and agents. | H11: RAG or agent basics | I11: Plant an instruction inside a document your RAG app retrieves; document whether it executes, then add one mitigation and re-test. | J11: Not started | K11: No
A12: P11 | B12: Should-read | C12: Training Compute-Optimal Large Language Models (Chinchilla) | D12: Hoffmann et al. | E12: 2022 | F12: https://arxiv.org/abs/2203.15556 | G12: Data vs parameters trade-off; explains why small models trained on more tokens win. | H12: P02 | I12: Use the paper's rule of thumb to estimate compute-optimal tokens for 1B, 8B and 70B models and compare with what recent open models report. | J12: Not started | K12: No
A13: P12 | B13: Should-read | C13: Chain-of-Thought Prompting Elicits Reasoning in Large Language Models | D13: Wei et al. | E13: 2022 | F13: https://arxiv.org/abs/2201.11903 | G13: Origin of step-by-step reasoning prompts. | H13: Prompting | I13: Compare direct answer vs CoT on 50 math word problems for a small and a large model. | J13: Not started | K13: No
... A42: P41 | B42: Advanced | C42: Generative Agents: Interactive Simulacra of Human Behavior | D42: Park et al. | E42: 2023 | F42: https://arxiv.org/abs/2304.03442 | G42: Memory stream, reflection and planning architecture for long-running agents. | H42: P05 | I42: Implement importance-weighted memory retrieval for a support agent. | J42: Not started | K42: No

Sheet Certifications
A1: ID | B1: Category | C1: Certification | D1: Code | E1: Vendor | F1: Level | G1: Link | H1: Status (Sep 2026) | I1: Exam | J1: Cost | K1: Validity | L1: Prerequisites | M1: Preparation | N1: Skills covered | O1: Best for | P1: Our read | Q1: My decision | R1: Exam date | S1: Result
A2: X01 | B2: Foundation | C2: AWS Certified AI Practitioner | D2: AIF-C01 | E2: AWS | F2: Foundational | G2: https://aws.amazon.com/certification/certified-ai-practitioner/ | H2: Active | I2: 90 min, 65 questions, online or test centre | J2: USD 100 | K2: 3 years | L2: None; ~6 months exposure to AI on AWS recommended | M2: AWS Skill Builder exam prep plan; AWS docs on Bedrock and SageMaker | N2: AI/ML concepts, GenAI use cases, responsible AI, AWS AI services | O2: Non-tech, college students | P2: Only for non-tech and early students who need a first structured milestone. Not an engineering signal.
A3: X02 | B3: Foundation | C3: Microsoft Certified: Azure AI Fundamentals | D3: AI-901 | E3: Microsoft | F3: Fundamentals | G3: https://learn.microsoft.com/en-us/credentials/certifications/azure-ai-fundamentals/ | H3: Active. AI-901 replaced AI-900, which retired on 30 June 2026. | I3: Pearson VUE; includes hands-on Microsoft Foundry scenarios and reading Python | J3: USD 99 in the US; lower regional pricing in India | K3: Does not expire | L3: None | M3: Microsoft Learn free learning path; Microsoft Learn AI Skills events sometimes offer exam vouchers | N3: GenAI and agent basics on Microsoft Foundry, responsible AI | O3: Non-tech, college students | P3: Cheapest recognised starter credential for Indian students. Do not stop here.
A4: X03 | B4: Foundation | C4: Google Cloud Certified Generative AI Leader | D4: Generative AI Leader | E4: Google Cloud | F4: Foundational | G4: https://cloud.google.com/learn/certification/generative-ai-leader | H4: Active | I4: 90 min, 50-60 questions | J4: USD 99 | K4: 3 years | L4: None | M4: Google Cloud Skills Boost Generative AI Leader path | N4: GenAI strategy, business use cases, governance on Google Cloud | O4: Non-tech professionals, managers | P4: For managers and product people moving toward AI. Engineers should skip it.
A5: X04 | B5: GenAI/LLM | C5: NVIDIA-Certified Associate: Generative AI LLMs | D5: NCA-GENL | E5: NVIDIA | F5: Associate | G5: https://www.nvidia.com/en-us/learn/certification/generative-ai-llm-associate/ | H5: Active | I5: 1 hour, online proctored | J5: USD 125 | K5: 2 years | L5: Basic understanding of ML and LLMs | M5: NVIDIA DLI courses; exam study guide on the certification page | N5: LLM fundamentals, prompting, data preparation, experimentation, NVIDIA tooling basics | O5: College students, Beginner track | P5: Reasonable first technical cert for students targeting GPU-heavy companies.
A6: X05 | B6: GenAI/LLM | C6: NVIDIA-Certified Associate: Generative AI Multimodal | D6: NCA-GENM | E6: NVIDIA | F6: Associate | G6: https://www.nvidia.com/en-us/learn/certification/generative-ai-multimodal-associate/ | H6: Active | I6: 1 hour, online proctored | J6: USD 125 | K6: 2 years | L6: Basic ML knowledge | M6: NVIDIA DLI multimodal courses | N6: Vision, audio and multimodal model concepts | O6: Multimodal-focused learners | P6: Optional. Only if your capstone is multimodal.
A7: X06 | B7: AI engineering | C7: AWS Certified Machine Learning Engineer – Associate | D7: MLA-C01 | E7: AWS | F7: Associate | G7: https://aws.amazon.com/certification/certified-machine-learning-engineer-associate/ | H7: Active | I7: 130 min, 65 questions | J7: USD 150 | K7: 3 years | L7: ~1 year with SageMaker and AWS services recommended | M7: AWS Skill Builder; hands-on SageMaker labs | N7: Data prep, model training, deployment, MLOps and monitoring on AWS | O7: Data Scientist, ML Engineer | P7: Good for Data Scientist and ML Engineer tracks in AWS-heavy companies.
A8: X07 | B8: GenAI/LLM | C8: AWS Certified Generative AI Developer – Professional | D8: AIP-C01 | E8: AWS | F8: Professional | G8: https://aws.amazon.com/certification/certified-generative-ai-developer-professional/ | H8: Active (beta ended 31 March 2026). Check page for current exam version. | I8: 65 scored + 10 unscored questions | J8: USD 300 | K8: 3 years | L8: Hands-on experience building GenAI apps on AWS recommended | M8: AWS Skill Builder; Bedrock workshops; build Project 2 and 3 on Bedrock | N8: RAG on Bedrock, agents with action groups, guardrails, cost and latency optimization, troubleshooting | O8: SWE, Agent Engineer, Forward-Deployed | P8: The strongest AWS signal for this role. Pick it if your target employers run on AWS.
A9: X08 | B9: AI engineering | C9: Microsoft Certified: Azure AI Apps and Agents Developer Associate | D9: AI-103 | E9: Microsoft | F9: Associate | G9: https://learn.microsoft.com/en-us/credentials/certifications/azure-ai-apps-and-agents-developer-associate/ | H9: Active. Replaced AI-102 (Azure AI Engineer Associate), which retired on 30 June 2026. | I9: ~120 min, Pearson VUE | J9: USD 165 in the US; regional pricing in India | K9: 1 year; free online renewal assessment | L9: Python and Azure basics recommended | M9: Microsoft Learn AI-103 learning paths and practice assessment | N9: Generative AI and agentic solutions on Microsoft Foundry, planning Azure AI solutions, vision, text analysis, information extraction | O9: Working professionals in services firms and GCCs | P9: Best choice for Indian IT services and GCC roles on the Microsoft stack.
A10: X09 | B10: AI engineering | C10: Google Cloud Professional Machine Learning Engineer | D10: PMLE | E10: Google Cloud | F10: Professional | G10: https://cloud.google.com/learn/certification/machine-learning-engineer | H10: Active. Exam updated in 2026 with more GenAI and agent coverage. | I10: 120 min, 50-60 questions | J10: USD 200 | K10: 2 years | L10: 3+ years industry experience recommended by Google | M10: Google Cloud Skills Boost ML Engineer path; Vertex AI labs | N10: ML solution design, Vertex AI pipelines, serving, monitoring, GenAI and agents on Google Cloud | O10: ML Engineer, Platform | P10: Strong for ML Engineer and Platform tracks in Google Cloud shops.
A11: X10 | B11: AI engineering | C11: Databricks Certified Generative AI Engineer Associate | D11: GenAI Engineer Associate | E11: Databricks | F11: Associate | G11: https://www.databricks.com/learn/certification/genai-engineer-associate | H11: Active | I11: Proctored, scenario-based | J11: USD 200 | K11: 2 years | L11: None formal; ~6 months hands-on recommended | M11: Databricks Academy Generative AI Engineering path | N11: RAG with Vector Search, Model Serving, MLflow, Unity Catalog governance, evaluation and monitoring | O11: Data Scientist, Data Engineer moving to AI | P11: Very relevant for data-heavy enterprises and GCCs that run Databricks.
A12: X11 | B12: GenAI/LLM | C12: NVIDIA-Certified Professional: Generative AI LLMs | D12: NCP-GENL | E12: NVIDIA | F12: Professional | G12: https://www.nvidia.com/en-us/learn/certification/generative-ai-llm-professional/ | H12: Active | I12: 2 hours, online proctored | J12: USD 200 | K12: 2 years | L12: 2-3 years of AI/ML experience recommended | M12: NVIDIA DLI; NeMo, TensorRT-LLM and Triton hands-on | N12: LLM training, fine-tuning, optimization, deployment with NVIDIA stack | O12: ML Engineer, Infra | P12: Good for ML Engineer and Infra tracks.
A13: X12 | B13: Agentic AI | C13: NVIDIA-Certified Professional: Agentic AI | D13: NCP-AAI | E13: NVIDIA | F13: Professional | G13: https://www.nvidia.com/en-us/learn/certification/agentic-ai-professional/ | H13: Active | I13: 2 hours, online proctored | J13: USD 200 | K13: 2 years | L13: 1-2 years in AI/ML roles with hands-on agentic projects recommended | M13: NVIDIA DLI agent courses; NeMo Agent Toolkit; your Project 3 | N13: Agent architecture, multi-agent systems, evaluation, deployment, safety and governance | O13: Agent Engineer, Senior Engineer | P13: The most direct agent-focused certification available today. Vendor-neutral concepts, NVIDIA-flavoured tooling.
... A21: X20 | B21: Retired (do not pursue) | C21: Microsoft Certified: Azure AI Engineer Associate | D21: AI-102 | E21: Microsoft | F21: Associate | G21: https://learn.microsoft.com/en-us/credentials/certifications/exams/ai-102/ | H21: Retired on 30 June 2026. Replaced by AI-103. | I21: No longer offered | J21: n/a | K21: Existing holders keep it until renewal date passes | L21: n/a | M21: n/a | N21: n/a | O21: n/a | P21: Watch for outdated course ads still selling AI-102 prep.

Sheet Conferences
A1: ID | B1: Event | C1: Type | D1: Dates | E1: Month | F1: Location | G1: Online option | H1: Cost | I1: CFP | J1: Why attend | K1: Networking (1-5) | L1: Engineering (1-5) | M1: Status (Sep 2026) | N1: Link | O1: My plan | P1: Notes
A2: E01 | B2: Cypher 2026 | C2: India | D2: 7-9 Oct 2026 | E2: 2026-10 | F2: KTPO Whitefield, Bengaluru | G2: Selected content later on AIM channels | H2: Paid passes; student passes sometimes offered | I2: Closed for 2026 | J2: India's largest applied AI conference; strong GCC and enterprise presence | K2: 5 | L2: 3 | M2: Confirmed | N2: https://cypher.analyticsindiamag.com/
A3: E02 | B3: AI Engineer New York 2026 | C3: AI engineering | D3: 12-14 Oct 2026 | E3: 2026-10 | F3: New York, USA | G3: Talks published on YouTube (@aiDotEngineer) | H3: Paid | I3: Check site | J3: Practitioner talks on agents, evals and AI infrastructure | K3: 4 | L3: 5 | M3: Confirmed | N3: https://ai.engineer/nyc/2026
A4: E03 | B4: PyTorch Conference North America 2026 | C4: Infrastructure | D4: 20-21 Oct 2026 | E4: 2026-10 | F4: San Jose, California, USA | G4: Recordings on YouTube | H4: Paid; scholarships available | I4: Closed for 2026 | J4: Training, inference, compilers, vLLM and open model ecosystem | K4: 4 | L4: 5 | M4: Confirmed | N4: https://events.linuxfoundation.org/pytorch-conference-north-america/
A5: E04 | B5: EMNLP 2026 | C5: Research | D5: 24-29 Oct 2026 | E5: 2026-10 | F5: Budapest, Hungary | G5: Virtual registration usually available | H5: Paid; student rates | I5: Closed for 2026 | J5: NLP and LLM research, evaluation and multilingual work | K5: 4 | L5: 3 | M5: Confirmed | N5: https://2026.emnlp.org/
A6: E05 | B6: DevFest 2026 (Google Developer Groups, India cities incl. Hyderabad) | C6: India | D6: Oct-Dec 2026 (varies by city) | E6: 2026-11 | F6: Hyderabad, Bengaluru, Pune, Chennai, NCR, Mumbai and more | G6: Some sessions streamed | H6: Free or low cost | I6: Chapter-level calls for speakers | J6: Local talks, Gemini and Google Cloud workshops, first speaking opportunities | K6: 4 | L6: 3 | M6: Recurring; check chapter page | N6: https://gdg.community.dev/gdg-hyderabad/
A7: E06 | B7: KubeCon + CloudNativeCon North America 2026 | C7: Infrastructure | D7: 9-12 Nov 2026 | E7: 2026-11 | F7: Salt Lake City, Utah, USA | G7: Recordings on CNCF YouTube | H7: Paid; scholarships | I7: Closed for 2026 | J7: New AI inference and agentic track; model serving on Kubernetes | K7: 4 | L7: 5 | M7: Confirmed | N7: https://events.linuxfoundation.org/kubecon-cloudnativecon-north-america/
A8: E07 | B8: AI Engineer Code Summit 2026 | C8: AI engineering | D8: 10-12 Nov 2026 | E8: 2026-11 | F8: San Francisco, USA | G8: Talks on YouTube | H8: Paid | I8: Check site | J8: Coding agents and AI developer tooling | K8: 4 | L8: 5 | M8: Confirmed | N8: https://www.ai.engineer/code
A9: E08 | B9: Microsoft Ignite 2026 | C9: Cloud | D9: 17-20 Nov 2026 | E9: 2026-11 | F9: Moscone Center, San Francisco, USA | G9: Free online sessions | H9: In-person paid; online free | I9: n/a | J9: Microsoft Foundry, agent platform and Azure AI announcements that shape AI-103 content | K9: 3 | L9: 3 | M9: Confirmed | N9: https://ignite.microsoft.com/
A10: E09 | B10: The Fifth Elephant Winter 2026 | C10: India | D10: Nov 2026 | E10: 2026-11 | F10: Bengaluru + virtual | G10: Yes | H10: Paid; affordable | I10: Check Hasgeek | J10: Independent Indian data and AI engineering community with honest production talks | K10: 4 | L10: 5 | M10: Announced; exact dates on Hasgeek | N10: https://hasgeek.com/fifthelephant
A11: E10 | B11: AWS re:Invent 2026 | C11: Cloud | D11: 30 Nov - 4 Dec 2026 | E11: 2026-12 | F11: Las Vegas, USA | G11: Keynotes and many sessions streamed free | H11: In-person paid | I11: n/a | J11: Bedrock, agents and SageMaker launches; AIP-C01 relevant updates | K11: 4 | L11: 3 | M11: Confirmed | N11: https://reinvent.awsevents.com/
A12: E11 | B12: NeurIPS 2026 | C12: Research | D12: 6-12 Dec 2026 (Sydney); satellites 8-13 Dec (Atlanta), 9-13 Dec (Paris) | E12: 2026-12 | F12: Sydney, Australia + Atlanta + Paris | G12: Virtual pass usually offered | H12: Paid; student rates | I12: Closed for 2026 | J12: Top ML research venue; watch workshops on agents, evaluation and efficient inference | K12: 5 | L12: 3 | M12: Confirmed | N12: https://neurips.cc/
A13: E12 | B13: BioAsia 2027 | C13: India | D13: Feb 2027 (check site) | E13: 2027-02 | F13: Hyderabad | G13: Check site | H13: Paid | I13: n/a | J13: Life sciences and healthcare AI in Hyderabad's pharma GCC hub; useful for healthcare capstones | K13: 5 | L13: 2 | M13: Recurring; 2027 dates pending | N13: https://bioasia.in/
... A26: E23 | B26: PyCon India | C26: India | D26: Usually Sep-Oct each year | E26: 2027-09 | F26: Rotates across Indian cities | G26: Talks on YouTube | H26: Low cost; student tickets | I26: Opens mid-year | J26: Python community, first talk opportunity, hiring booths | K26: 5 | L26: 4 | M26: Recurring; check site for current edition | N26: https://in.pycon.org/

Sheet Communities
A1: ID | B1: Scope | C1: Community | D1: Type | E1: Link | F1: Focus | G1: How to use it | H1: Level | I1: Joined | J1: Last active | K1: Notes
A2: M01 | B2: Global | C2: Hugging Face Discord | D2: Discord | E2: https://huggingface.co/join/discord | F2: Open models, courses, study groups | G2: Join course channels while doing the Agents/MCP courses; answer beginner questions once you finish | H2: All | I2: No
A3: M02 | B3: Global | C3: MLOps Community | D3: Slack + meetups + podcast | E3: https://mlops.community/ | F3: Production ML and AI engineering | G3: Read #llmops and #agents; attend virtual meetups; local chapters exist in Indian cities | H3: Intermediate+ | I3: No
A4: M03 | B4: Global | C4: DataTalks.Club | D4: Slack + free courses | E4: https://datatalks.club/ | F4: Zoomcamps, data and AI engineering | G4: Join the LLM Zoomcamp cohort for peer review and deadlines | H4: Beginner+ | I4: No
A5: M04 | B5: Global | C5: Latent Space | D5: Newsletter + podcast + Discord | E5: https://www.latent.space/ | F5: AI engineering trends and practitioner interviews | G5: One episode a week during commute; join paper club | H5: Intermediate+ | I5: No
A6: M05 | B6: Global | C6: EleutherAI Discord | D6: Discord | E6: https://www.eleuther.ai/ | F6: Open research, interpretability, evaluation | G6: Research track: read, reproduce, contribute to lm-evaluation-harness | H6: Advanced | I6: No
A7: M06 | B7: Global | C7: GPU MODE | D7: Discord + YouTube lectures | E7: https://www.youtube.com/@GPUMODE | F7: CUDA, kernels, performance engineering | G7: Infra track: watch lectures, join kernel study groups | H7: Advanced | I7: No
A8: M07 | B8: Global | C8: OWASP GenAI Security Project | D8: Open project + Slack | E8: https://genai.owasp.org/ | F8: LLM and agent security guidance | G8: Security track: contribute to working groups; cite their Top 10 in threat models | H8: Intermediate+ | I8: No
A9: M08 | B9: Global | C9: MCP community (GitHub discussions) | D9: GitHub | E9: https://github.com/modelcontextprotocol | F9: Model Context Protocol spec, SDKs and servers | G9: Read spec discussions; contribute small fixes to SDKs or reference servers | H9: Intermediate+ | I9: No
A10: M09 | B10: Global | C10: r/LocalLLaMA | D10: Reddit | E10: https://www.reddit.com/r/LocalLLaMA/ | F10: Local and open-weight model deployment, benchmarks | G10: Useful for hardware and quantization reality checks; verify claims before repeating them | H10: All | I10: No
A11: M10 | B11: India | C11: AI Anytime community | D11: Discord + WhatsApp + YouTube | E11: https://aianytime-site.vercel.app/ | F11: Project-based AI engineering, open-source repos, office hours | G11: Share weekly progress, find project partners, get feedback on portfolio repos | H11: All | I11: No
A12: M11 | B12: India | C12: Hasgeek (The Fifth Elephant, Rootconf) | D12: Community events | E12: https://hasgeek.com/ | F12: Data, AI, infra and security engineering talks | G12: Attend online sessions; submit a talk once your capstone is done | H12: Intermediate+ | I12: No
A13: M12 | B13: India | C13: PyCon India and regional Python communities | D13: Conference + city meetups | E13: https://in.pycon.org/ | F13: Python ecosystem | G13: Find your city's Python meetup (PyDelhi, BangPypers, Hyderabad Python, PythonPune, ChennaiPy) | H13: All | I13: No
... A23: M22 | B23: Hyderabad | C23: HYSEA (Hyderabad Software Enterprises Association) | D23: Industry body | E23: https://www.hysea.in/ | F23: Hyderabad IT and GCC industry events | G23: Senior professionals: leadership and GCC networking | H23: Mid/Senior | I23: No

Sheet Lists
A1: 0. Non-Tech → AI Builder
A2: 1. Beginner → AI Engineer
A3: 2. Software Engineer → AI Engineer
A4: 3. Data Scientist → AI Engineer
A5: 4. ML Engineer → AI Engineer
A6: 5. Senior Engineer → AI Architect
A7: 6. Research Engineer
A8: 7. Agent Engineer
A9: 8. AI Platform / Infrastructure Engineer
A10: 9. AI Security Engineer
A11: 10. Forward-Deployed / AI Product Engineer
